Workbook

Sheet Funder Database April
A1: Funder ID | B1: Donor Name | C1: Organization | D1: Donor Type | E1: Stage | F1: Status | G1: Primary Contact Email | H1: Phone | I1: Region | J1: Giving Level | K1: First Gift Date | L1: First Gift Amount | M1: FY2023 Giving | N1: FY2024 Giving | O1: FY2025 Giving | P1: FY2026 Giving (YTD) | Q1: Lifetime Giving | R1: Multi-Year Pledge? | S1: Pledge Total | T1: Pledge Start FY | U1: Pledge End FY | V1: Current Pledge Year | W1: Annual Pledge Amount | X1: Fund / DAF | Y1: Gift Designation | Z1: Stewardship Owner | AA1: Last Contact Date | AB1: Last Contact Type | AC1: Next Action | AD1: Next Action Date | AE1: Board Member? | AF1: Advisory Council? | AG1: Event Attendance (Last 12mo) | AH1: Capacity Rating | AI1: Likelihood Rating | AJ1: Priority Score | AK1: Notes | AL1: Account Owner
A2: F-001 | B2: David & Rachel Kim | C2: Kim Family Trust | D2: Individual/Family | E2: Stewardship | F2: Active | G2: david.kim@kimfamilytrust.org | H2: (310) 555-6243 | I2: West Coast | J2: Transformational | K2: 03/15/2016 | L2: 100000 | M2: 350000 | N2: 400000 | O2: 450000 | P2: 500000 | Q2: =SUM(M2:P2) -> 1700000 | R2: Yes | S2: 2500000 | T2: FY2022 | U2: FY2027 | V2: 5 of 6 | W2: 450000 | X2: Kim Family DAF - Goldman Sachs Philanthropy Fund | Y2: Unrestricted / West Coast Initiative | Z2: Sarah Mitchell | AA2: 03/12/2026 | AB2: In-person meeting | AC2: Cultivation event planning at Kim residence | AD2: 05/01/2026 | AE2: No | AF2: No | AG2: 3 | AH2: A ($1M+) | AI2: Very High | AJ2: 10 | AK2: 10-year donor. Interested in West Coast expansion. Rachel hosting May gala cultivation event. | AL2: Lisa
A3: F-002 | B3: Margaret Chen | C3: Chen Family Foundation | D3: Foundation | E3: Stewardship | F3: Active | G3: margaret.chen@chenfamilyfdn.org | H3: (415) 555-2891 | I3: West Coast | J3: Major | K3: 09/20/2019 | L3: 50000 | M3: 150000 | N3: 200000 | O3: 250000 | P3: 250000 | Q3: =SUM(M3:P3) -> 850000 | R3: Yes | S3: 1250000 | T3: FY2024 | U3: FY2028 | V3: 3 of 5 | W3: 250000 | X3: Chen Family DAF - Fidelity Charitable | Y3: STEM Education | Z3: Sarah Mitchell | AA3: 02/28/2026 | AB3: Phone call | AC3: Finalize advisory board invitation | AD3: 04/15/2026 | AE3: No | AF3: Pending | AG3: 2 | AH3: A ($1M+) | AI3: High | AJ3: 9 | AK3: Connected us with Priya Ramanathan. Interested in advisory board. | AL3: Rafaela
A4: F-003 | B4: Alicia Gutierrez-Santos | C4: Santos Foundation | D4: Foundation | E4: Stewardship | F4: Active | G4: alicia@santosfoundation.org | H4: (713) 555-3476 | I4: Southwest | J4: Major | K4: 06/10/2021 | L4: 75000 | M4: 100000 | N4: 120000 | O4: 150000 | P4: 180000 | Q4: =SUM(M4:P4) -> 550000 | R4: Yes | S4: 900000 | T4: FY2024 | U4: FY2028 | V4: 3 of 5 | W4: 180000 | X4: Santos Foundation DAF - National Philanthropic Trust | Y4: STEM Education Pipeline | Z4: Maria Lopez | AA4: 03/05/2026 | AB4: Email | AC4: Coordinate joint site visit with Sandra Okonkwo | AD4: 04/20/2026 | AE4: No | AF4: No | AG4: 2 | AH4: B ($500K-$1M) | AI4: Very High | AJ4: 9 | AK4: Earmarked for STEM pipeline. Wants quarterly impact reports. Suggested joint site visit with Okonkwo. | AL4: Jack
A5: F-004 | B5: Robert Blackwell III | C5: Blackwell Industries | D5: Corporate | E5: Cultivation | F5: Active | G5: r.blackwell@blackwellindustries.com | H5: (212) 555-7634 | I5: Northeast | J5: Major | K5: 01/22/2026 | L5: 150000 | M5: 0 | N5: 0 | O5: 0 | P5: 150000 | Q5: =SUM(M5:P5) -> 150000 | R5: No | X5: Blackwell Giving Fund - Schwab Charitable | Y5: Northeast Programs | Z5: James Wright | AA5: 02/15/2026 | AB5: In-person meeting | AC5: Schedule second meeting; discuss multi-year | AD5: 04/30/2026 | AE5: No | AF5: No | AG5: 1 | AH5: A ($1M+) | AI5: Medium | AJ5: 8 | AK5: First-time major donor. Board referral from Thomas Fitzgerald. High capacity prospect. | AL5: Lisa
A6: F-005 | B6: James & Dorothy Whitfield | C6: Whitfield Group | D6: Individual/Family | E6: Stewardship | F6: Active | G6: jwhitfield@whitfieldgroup.net | H6: (312) 555-8819 | I6: Midwest | J6: Major | K6: 11/01/2018 | L6: 50000 | M6: 75000 | N6: 85000 | O6: 100000 | P6: 100000 | Q6: =SUM(M6:P6) -> 360000 | R6: Yes | S6: 500000 | T6: FY2024 | U6: FY2028 | V6: 3 of 5 | W6: 100000 | X6: Whitfield Family DAF - Vanguard Charitable | Y6: Unrestricted | Z6: Sarah Mitchell | AA6: 01/20/2026 | AB6: Holiday card + call | AC6: Annual renewal meeting | AD6: 09/15/2026 | AE6: No | AF6: No | AG6: 1 | AH6: B ($500K-$1M) | AI6: Very High | AJ6: 9 | AK6: Steady annual renewal. Very loyal. | AL6: Lisa
A7: F-006 | B7: Naomi Ashford | C7: Ashford Philanthropic Group | D7: Foundation | E7: Stewardship | F7: Active | G7: nashford@ashfordphilanthropy.org | H7: (503) 555-7789 | I7: Pacific NW | J7: Major | K7: 04/22/2020 | L7: 60000 | M7: 80000 | N7: 100000 | O7: 110000 | P7: 125000 | Q7: =SUM(M7:P7) -> 415000 | R7: Yes | S7: 625000 | T7: FY2024 | U7: FY2028 | V7: 3 of 5 | W7: 125000 | X7: Ashford DAF - BNY Mellon | Y7: Rural Program Expansion | Z7: Maria Lopez | AA7: 03/15/2026 | AB7: Email | AC7: Send Q1 impact report | AD7: 04/10/2026 | AE7: No | AF7: Yes | AG7: 2 | AH7: B ($500K-$1M) | AI7: High | AJ7: 8 | AK7: Earmarked for rural expansion. Very engaged with program outcomes. | AL7: Rafaela
A8: F-007 | B8: Priya Ramanathan | C8: Ramanathan & Associates | D8: Corporate | E8: Stewardship | F8: Active | G8: priya@ramanathan-assoc.com | H8: (617) 555-4102 | I8: Northeast | J8: Mid-Level | K8: 08/15/2022 | L8: 25000 | M8: 25000 | N8: 35000 | O8: 50000 | P8: 75000 | Q8: =SUM(M8:P8) -> 185000 | R8: No | X8: Direct | Y8: STEM Education | Z8: James Wright | AA8: 02/03/2026 | AB8: Email | AC8: Thank you + impact report | AD8: 04/15/2026 | AE8: No | AF8: No | AG8: 1 | AH8: C ($100K-$500K) | AI8: High | AJ8: 7 | AK8: Referred by Margaret Chen. Increased from $50K to $75K this year. | AL8: Jack
A9: F-008 | B9: Michael & Patricia Novak | C9: Novak Family Foundation | D9: Foundation | E9: Stewardship | F9: Active | G9: mnovak@novakfamilyfdn.org | H9: (847) 555-4412 | I9: Midwest | J9: Mid-Level | K9: 02/20/2021 | L9: 40000 | M9: 50000 | N9: 65000 | O9: 75000 | P9: 90000 | Q9: =SUM(M9:P9) -> 280000 | R9: No | X9: Novak Family DAF - Community Foundation | Y9: Pell-Eligible Student Scholarships | Z9: Sarah Mitchell | AA9: 03/18/2026 | AB9: Phone call | AC9: Prepare renewal proposal | AD9: 05/01/2026 | AE9: No | AF9: No | AG9: 1 | AH9: B ($500K-$1M) | AI9: High | AJ9: 8 | AK9: Focus on Pell-eligible students in Midwest. Opportunity for programmatic partnership. | AL9: Lisa
A10: F-009 | B10: Sandra Okonkwo | C10: Okonkwo Ventures | D10: Corporate | E10: Cultivation | F10: Active | G10: sokonkwo@okonkwoventures.com | H10: (404) 555-1357 | I10: Southeast | J10: Mid-Level | K10: 02/14/2026 | L10: 50000 | M10: 0 | N10: 0 | O10: 0 | P10: 50000 | Q10: =SUM(M10:P10) -> 50000 | R10: No | X10: Direct | Y10: Scholarship Program | Z10: Maria Lopez | AA10: 02/14/2026 | AB10: Event follow-up | AC10: Joint site visit with Gutierrez-Santos | AD10: 04/20/2026 | AE10: No | AF10: No | AG10: 1 | AH10: C ($100K-$500K) | AI10: Medium | AJ10: 6 | AK10: Event follow-up conversion. Shares interest in scholarship program with Gutierrez-Santos. | AL10: Lisa
A11: F-010 | B11: Thomas Fitzgerald | C11: Fitzgerald & Moore LLP | D11: Corporate | E11: Stewardship | F11: Active | G11: tfitzgerald@fitzmoore.com | H11: (202) 555-9088 | I11: Mid-Atlantic | J11: Mid-Level | K11: 05/10/2020 | L11: 15000 | M11: 15000 | N11: 20000 | O11: 25000 | P11: 25000 | Q11: =SUM(M11:P11) -> 85000 | R11: No | X11: Direct | Y11: Unrestricted + Pro Bono Legal | Z11: James Wright | AA11: 03/01/2026 | AB11: In-person meeting | AC11: Discuss pro bono capacity for next FY | AD11: 04/30/2026 | AE11: No | AF11: No | AG11: 2 | AH11: C ($100K-$500K) | AI11: High | AJ11: 7 | AK11: Also provides pro bono legal support. Referred Robert Blackwell III. | AL11: Jack
A12: F-011 | B12: William R. Thornton | C12: Thornton Capital Partners | D12: Corporate | E12: Qualification | F12: Prospect | G12: wthornton@thorntoncap.com | H12: (646) 555-5521 | I12: Northeast | J12: Mid-Level | K12: 10/05/2025 | L12: 60000 | M12: 0 | N12: 0 | O12: 60000 | P12: 60000 | Q12: =SUM(M12:P12) -> 120000 | R12: No | X12: Direct | Y12: Unrestricted | Z12: James Wright | AA12: 03/10/2026 | AB12: In-person meeting | AC12: Prepare board nomination package | AD12: 04/15/2026 | AE12: No | AF12: No | AG12: 2 | AH12: A ($1M+) | AI12: Medium | AJ12: 8 | AK12: Strong board prospect. Requested meeting with ED. Deepening engagement since fall reception. | AL12: Lisa
A13: F-012 | B13: Evelyn Tran | C13: Tran Holdings LLC | D13: Corporate | E13: Cultivation | F13: Prospect | G13: evelyn.tran@tranholdings.com | H13: (408) 555-2106 | I13: West Coast | J13: Entry | K13: 12/01/2025 | L13: 35000 | M13: 0 | N13: 0 | O13: 35000 | P13: 35000 | Q13: =SUM(M13:P13) -> 70000 | R13: No | X13: Direct | Y13: Alumni Scholarship | Z13: Sarah Mitchell | AA13: 03/22/2026 | AB13: Email | AC13: Follow up on named scholarship fund interest | AD13: 04/30/2026 | AE13: No | AF13: No | AG13: 1 | AH13: A ($1M+) | AI13: Low | AJ13: 7 | AK13: Alumni, Class of 2005. Company just completed Series C. Interested in named scholarship fund. | AL13: Lisa
A14: F-013 | B14: Hiroshi Tanaka | C14: Tanaka Biotech Inc. | D14: Corporate | E14: Identification | F14: Prospect | G14: htanaka@tanakabiotech.com | H14: (858) 555-3891 | I14: West Coast | J14: None | M14: 0 | N14: 0 | O14: 0 | P14: 0 | Q14: =SUM(M14:P14) -> 0 | R14: No | Y14: STEM Education | Z14: Maria Lopez | AA14: 01/10/2026 | AB14: Research | AC14: Request intro through Margaret Chen | AD14: 04/15/2026 | AE14: No | AF14: No | AG14: 0 | AH14: A ($1M+) | AI14: Low | AJ14: 7 | AK14: UC San Diego connection. Biotech IPO 2024. Interested in STEM education per public statements. | AL14: Lisa
A15: F-014 | B15: Denise & Marcus Hargrove | C15: Hargrove Family Fund | D15: Individual/Family | E15: Identification | F15: Prospect | G15: dhargrove@hargrovefund.org | H15: (404) 555-8822 | I15: Southeast | J15: None | M15: 0 | N15: 0 | O15: 0 | P15: 0 | Q15: =SUM(M15:P15) -> 0 | R15: No | Z15: James Wright | AA15: 12/15/2025 | AB15: Research | AC15: Outreach via annual appeal mailing | AD15: 05/01/2026 | AE15: No | AF15: No | AG15: 0 | AH15: B ($500K-$1M) | AI15: Low | AJ15: 6 | AK15: Atlanta-based philanthropy family. Focus on education equity. Identified via peer screening. | AL15: Jack
A16: F-015 | B16: Victoria Langston-Reed | C16: Reed Foundation | D16: Foundation | E16: Solicitation | F16: Prospect | G16: vlreed@reedfoundation.org | H16: (617) 555-6100 | I16: Northeast | J16: None | M16: 0 | N16: 0 | O16: 0 | P16: 0 | Q16: =SUM(M16:P16) -> 0 | R16: No | Y16: Scholarship / General | Z16: Sarah Mitchell | AA16: 03/28/2026 | AB16: Proposal submitted | AC16: Await foundation board decision | AD16: 06/01/2026 | AE16: No | AF16: No | AG16: 1 | AH16: A ($1M+) | AI16: Medium | AJ16: 8 | AK16: $200K proposal submitted for scholarship endowment. Foundation board meets quarterly. | AL16: Lisa
A17: F-016 | B17: Gregory & Susan Patel | C17: Patel Family Trust | D17: Individual/Family | E17: Re-engagement | F17: Lapsed | G17: gpatel@patelfamilytrust.org | H17: (312) 555-2200 | I17: Midwest | J17: Mid-Level | K17: 06/01/2018 | L17: 25000 | M17: 50000 | N17: 40000 | O17: 0 | P17: 0 | Q17: =SUM(M17:P17) -> 90000 | R17: No | X17: Patel Family DAF - Schwab | Y17: Unrestricted | Z17: James Wright | AA17: 11/20/2025 | AB17: Phone call (voicemail) | AC17: Send personalized re-engagement letter | AD17: 04/10/2026 | AE17: No | AF17: Yes (Former) | AG17: 0 | AH17: B ($500K-$1M) | AI17: Medium | AJ17: 7 | AK17: Last gift FY2024. Missed FY2025 renewal. Was on advisory council. Personal outreach needed. | AL17: Lisa
A18: F-017 | B18: Diana Kowalski | C18: Kowalski Media Group | D18: Corporate | E18: Re-engagement | F18: Lapsed | G18: dkowalski@kowalskimedia.com | H18: (646) 555-4477 | I18: Northeast | J18: Entry | K18: 09/15/2020 | L18: 10000 | M18: 15000 | N18: 10000 | O18: 0 | P18: 0 | Q18: =SUM(M18:P18) -> 25000 | R18: No | X18: Direct | Y18: Unrestricted | Z18: Maria Lopez | AA18: 10/01/2025 | AB18: Email (no response) | AC18: Try phone outreach | AD18: 04/15/2026 | AE18: No | AF18: No | AG18: 0 | AH18: C ($100K-$500K) | AI18: Low | AJ18: 5 | AK18: Last gift FY2024. No response to renewal emails. Try phone. | AL18: Jack
A19: F-018 | B19: Lawrence Bennett | C19: Bennett Capital LLC | D19: Corporate | E19: Closed - Declined | F19: Inactive | G19: lbennett@bennettcap.com | H19: (415) 555-9900 | I19: West Coast | J19: None | M19: 0 | N19: 0 | O19: 0 | P19: 0 | Q19: =SUM(M19:P19) -> 0 | R19: No | Z19: Sarah Mitchell | AA19: 09/15/2025 | AB19: Phone call | AC19: Monitor; revisit in 18 months | AD19: 03/15/2027 | AE19: No | AF19: No | AG19: 1 | AH19: A ($1M+) | AI19: Very Low | AJ19: 6 | AK19: Declined after solicitation meeting. Cited other philanthropic priorities. Polite; door not closed. | AL19: Rafaela
A20: F-019 | B20: Catherine & James Moreau | C20: Moreau Foundation | D20: Foundation | E20: Stewardship | F20: Active | G20: cmoreau@moreaufoundation.org | H20: (504) 555-3321 | I20: Southeast | J20: Major | K20: 01/10/2019 | L20: 80000 | M20: 100000 | N20: 120000 | O20: 140000 | P20: 160000 | Q20: =SUM(M20:P20) -> 520000 | R20: Yes | S20: 800000 | T20: FY2024 | U20: FY2028 | V20: 3 of 5 | W20: 160000 | X20: Moreau Foundation DAF - Fidelity | Y20: First-Generation Student Support | Z20: Sarah Mitchell | AA20: 03/20/2026 | AB20: Phone call | AC20: Discuss program expansion opportunities | AD20: 05/10/2026 | AE20: No | AF20: No | AG20: 2 | AH20: B ($500K-$1M) | AI20: Very High | AJ20: 9 | AK20: New Orleans-based. Deep interest in first-gen students. Annual site visits. | AL20: Jack
A21: F-020 | B21: Richard Cheng | C21: Cheng Dynamics | D21: Corporate | E21: Stewardship | F21: Active | G21: rcheng@chengdynamics.com | H21: (650) 555-8812 | I21: West Coast | J21: Mid-Level | K21: 03/01/2022 | L21: 30000 | M21: 30000 | N21: 45000 | O21: 55000 | P21: 70000 | Q21: =SUM(M21:P21) -> 200000 | R21: No | X21: Direct | Y21: STEM Education | Z21: Maria Lopez | AA21: 02/20/2026 | AB21: Email | AC21: Invite to May gala | AD21: 04/20/2026 | AE21: No | AF21: No | AG21: 2 | AH21: C ($100K-$500K) | AI21: High | AJ21: 7 | AK21: Growing engagement. Employee matching program potential. | AL21: Rafaela
A22: F-021 | B22: Amara Osei-Mensah | C22: Osei-Mensah Family Trust | D22: Individual/Family | E22: Stewardship | F22: Active | G22: aosei@oseimensah.org | H22: (770) 555-6644 | I22: Southeast | J22: Mid-Level | K22: 06/15/2021 | L22: 25000 | M22: 35000 | N22: 40000 | O22: 50000 | P22: 65000 | Q22: =SUM(M22:P22) -> 190000 | R22: No | X22: Osei-Mensah DAF - Vanguard | Y22: Scholarship Program | Z22: James Wright | AA22: 01/30/2026 | AB22: In-person meeting | AC22: Propose multi-year pledge | AD22: 04/25/2026 | AE22: No | AF22: No | AG22: 1 | AH22: B ($500K-$1M) | AI22: High | AJ22: 8 | AK22: Atlanta-based. Increasing annually. Ready for major gift conversation. | AL22: Jack
A23: F-022 | B23: Patricia & Leonard Dubois | C23: Dubois Charitable Fund | D23: Individual/Family | E23: Stewardship | F23: Active | G23: pdubois@duboisfund.org | H23: (617) 555-1198 | I23: Northeast | J23: Major | K23: 09/01/2017 | L23: 75000 | M23: 100000 | N23: 100000 | O23: 100000 | P23: 100000 | Q23: =SUM(M23:P23) -> 400000 | R23: Yes | S23: 500000 | T23: FY2023 | U23: FY2027 | V23: 4 of 5 | W23: 100000 | X23: Dubois DAF - BNY Mellon | Y23: Unrestricted | Z23: Sarah Mitchell | AA23: 12/15/2025 | AB23: Holiday card + call | AC23: Final pledge year discussion; renewal strategy | AD23: 06/01/2026 | AE23: Yes | AF23: No | AG23: 2 | AH23: A ($1M+) | AI23: Very High | AJ23: 10 | AK23: Board member. Entering final pledge year. Need to discuss renewal or increase. | AL23: Lisa
A24: F-023 | B24: Kenji & Yuki Watanabe | C24: Watanabe Group | D24: Corporate | E24: Cultivation | F24: Active | G24: kwatanabe@watanabegroup.co | H24: (206) 555-4455 | I24: Pacific NW | J24: Mid-Level | K24: 11/15/2024 | L24: 40000 | M24: 0 | N24: 0 | O24: 40000 | P24: 55000 | Q24: =SUM(M24:P24) -> 95000 | R24: No | X24: Direct | Y24: Rural Program | Z24: Maria Lopez | AA24: 03/01/2026 | AB24: In-person meeting | AC24: Tour rural program sites | AD24: 05/15/2026 | AE24: No | AF24: No | AG24: 1 | AH24: C ($100K-$500K) | AI24: Medium | AJ24: 6 | AK24: Seattle-based. Second gift indicates deepening. Schedule site visit. | AL24: Lisa
A25: F-024 | B25: Helen Markovich | C25: Markovich Partners LLC | D25: Corporate | E25: Stewardship | F25: Active | G25: hmarkovich@markovichpartners.com | H25: (312) 555-7733 | I25: Midwest | J25: Mid-Level | K25: 04/20/2020 | L25: 20000 | M25: 25000 | N25: 30000 | O25: 35000 | P25: 45000 | Q25: =SUM(M25:P25) -> 135000 | R25: No | X25: Direct | Y25: Unrestricted | Z25: James Wright | AA25: 02/10/2026 | AB25: Email | AC25: Send FY2026 impact summary | AD25: 04/15/2026 | AE25: No | AF25: Yes | AG25: 2 | AH25: C ($100K-$500K) | AI25: High | AJ25: 7 | AK25: Advisory council member. Consistent growth. Midwest business network connections. | AL25: Lisa
A26: F-025 | B26: Raj & Sunita Kapoor | C26: Kapoor Family Foundation | D26: Foundation | E26: Stewardship | F26: Active | G26: rkapoor@kapoorfamilyfdn.org | H26: (713) 555-9922 | I26: Southwest | J26: Major | K26: 02/28/2020 | L26: 50000 | M26: 75000 | N26: 90000 | O26: 100000 | P26: 120000 | Q26: =SUM(M26:P26) -> 385000 | R26: Yes | S26: 600000 | T26: FY2025 | U26: FY2029 | V26: 2 of 5 | W26: 120000 | X26: Kapoor Family DAF - Goldman Sachs | Y26: STEM Education Pipeline | Z26: Maria Lopez | AA26: 03/10/2026 | AB26: Phone call | AC26: Quarterly impact report delivery | AD26: 04/10/2026 | AE26: No | AF26: No | AG26: 2 | AH26: A ($1M+) | AI26: High | AJ26: 9 | AK26: Houston-based. Strong alignment with STEM pipeline. Want to see expansion to Texas. | AL26: Lisa
A27: F-026 | B27: Franklin & Anne Beaumont | C27: Beaumont Group | D27: Individual/Family | E27: Stewardship | F27: Active | G27: fbeaumont@beaumontgroup.com | H27: (214) 555-2288 | I27: Southwest | J27: Mid-Level | K27: 07/01/2021 | L27: 20000 | M27: 25000 | N27: 30000 | O27: 40000 | P27: 50000 | Q27: =SUM(M27:P27) -> 145000 | R27: No | X27: Direct | Y27: General Scholarship | Z27: Sarah Mitchell | AA27: 01/15/2026 | AB27: Holiday card + call | AC27: Annual renewal ask | AD27: 09/01/2026 | AE27: No | AF27: No | AG27: 1 | AH27: C ($100K-$500K) | AI27: High | AJ27: 7 | AK27: Dallas-based. Reliable renewals. Potential for multi-year commitment. | AL27: Jack
A28: F-027 | B28: Nadia El-Amin | C28: El-Amin Consulting Group | D28: Corporate | E28: Stewardship | F28: Active | G28: nelamin@elamingroup.com | H28: (202) 555-6655 | I28: Mid-Atlantic | J28: Entry | K28: 10/01/2023 | L28: 10000 | M28: 0 | N28: 0 | O28: 10000 | P28: 15000 | Q28: =SUM(M28:P28) -> 25000 | R28: No | X28: Direct | Y28: Unrestricted | Z28: James Wright | AA28: 03/15/2026 | AB28: Email | AC28: Cultivation lunch | AD28: 05/01/2026 | AE28: No | AF28: No | AG28: 1 | AH28: C ($100K-$500K) | AI28: Medium | AJ28: 6 | AK28: DC-based consultant. Growing engagement. Connected to policy networks. | AL28: Lisa
A29: F-028 | B29: George & Linda Stratton | C29: Stratton Industries | D29: Corporate | E29: Qualification | F29: Prospect | G29: gstratton@strattonindustries.com | H29: (704) 555-1122 | I29: Southeast | J29: None | M29: 0 | N29: 0 | O29: 0 | P29: 0 | Q29: =SUM(M29:P29) -> 0 | R29: No | Y29: Unrestricted | Z29: James Wright | AA29: 02/01/2026 | AB29: Research | AC29: Request meeting through Thornton connection | AD29: 04/20/2026 | AE29: No | AF29: No | AG29: 0 | AH29: A ($1M+) | AI29: Low | AJ29: 7 | AK29: Charlotte manufacturing. Peer connection through William Thornton. Philanthropic history in education. | AL29: Lisa
A30: F-029 | B30: Isabelle Fontaine | C30: Fontaine Arts & Education Trust | D30: Foundation | E30: Cultivation | F30: Prospect | G30: ifontaine@fontainetrust.org | H30: (415) 555-5567 | I30: West Coast | J30: None | M30: 0 | N30: 0 | O30: 0 | P30: 0 | Q30: =SUM(M30:P30) -> 0 | R30: No | Y30: Arts + STEM Integration | Z30: Sarah Mitchell | AA30: 03/25/2026 | AB30: In-person meeting | AC30: Submit LOI for arts-STEM integration grant | AD30: 05/01/2026 | AE30: No | AF30: No | AG30: 1 | AH30: B ($500K-$1M) | AI30: Medium | AJ30: 7 | AK30: SF-based trust focused on arts and education. Met at conference. Very aligned with new arts-STEM program. | AL30: Lisa
A31: F-030 | B31: Marcus & Tanya Robinson | C31: Robinson Legacy Fund | D31: Individual/Family | E31: Identification | F31: Prospect | G31: mrobinson@robinsonlegacy.org | H31: (404) 555-8890 | I31: Southeast | J31: None | M31: 0 | N31: 0 | O31: 0 | P31: 0 | Q31: =SUM(M31:P31) -> 0 | R31: No | Z31: Maria Lopez | AA31: 01/20/2026 | AB31: Research | AC31: Add to annual gala invite list | AD31: 04/15/2026 | AE31: No | AF31: No | AG31: 0 | AH31: B ($500K-$1M) | AI31: Low | AJ31: 6 | AK31: Atlanta philanthropists. Education equity focus. Identified through Hargrove network. | AL31: Lisa
A32: F-031 | B32: Dr. Angela Vasquez-Torres | C32: Vasquez-Torres Medical Foundation | D32: Foundation | E32: Solicitation | F32: Prospect | G32: avasquez@vtmedfoundation.org | H32: (305) 555-7712 | I32: Southeast | J32: None | M32: 0 | N32: 0 | O32: 0 | P32: 0 | Q32: =SUM(M32:P32) -> 0 | R32: No | Y32: Health Sciences Scholarship | Z32: James Wright | AA32: 03/30/2026 | AB32: Proposal submitted | AC32: Follow up after board review | AD32: 06/15/2026 | AE32: No | AF32: No | AG32: 1 | AH32: B ($500K-$1M) | AI32: Medium | AJ32: 7 | AK32: $150K proposal for health sciences scholarships. Miami-based. Board meets in June. | AL32: Rafaela
A33: F-032 | B33: Arthur & Elaine Worthington | C33: Worthington Trust | D33: Individual/Family | E33: Qualification | F33: Prospect | G33: aworthington@worthingtontrust.com | H33: (860) 555-3344 | I33: Northeast | J33: None | M33: 0 | N33: 0 | O33: 0 | P33: 0 | Q33: =SUM(M33:P33) -> 0 | R33: No | Y33: Endowment | Z33: Sarah Mitchell | AA33: 02/10/2026 | AB33: Phone call | AC33: Schedule campus visit | AD33: 04/25/2026 | AE33: No | AF33: No | AG33: 0 | AH33: A ($1M+) | AI33: Low | AJ33: 7 | AK33: Connecticut old money. Endowment-focused giving. Warm intro from Dubois. | AL33: Jack
A34: F-033 | B34: Carmen Delgado-Ruiz | C34: Delgado Enterprises | D34: Corporate | E34: Cultivation | F34: Prospect | G34: cdelgado@delgadoenterprises.com | H34: (210) 555-4411 | I34: Southwest | J34: Entry | K34: 12/15/2025 | L34: 15000 | M34: 0 | N34: 0 | O34: 0 | P34: 15000 | Q34: =SUM(M34:P34) -> 15000 | R34: No | X34: Direct | Y34: STEM Education | Z34: Maria Lopez | AA34: 12/15/2025 | AB34: Event follow-up | AC34: Schedule coffee meeting | AD34: 04/15/2026 | AE34: No | AF34: No | AG34: 1 | AH34: C ($100K-$500K) | AI34: Medium | AJ34: 6 | AK34: San Antonio-based. Initial gift at holiday event. Tech company founder. STEM aligned. | AL34: Rafaela
A35: F-034 | B35: Howard & Jean Prescott | C35: Prescott Foundation | D35: Foundation | E35: Re-engagement | F35: Lapsed | G35: hprescott@prescottfdn.org | H35: (203) 555-6677 | I35: Northeast | J35: Major | K35: 03/01/2016 | L35: 100000 | M35: 120000 | N35: 100000 | O35: 50000 | P35: 0 | Q35: =SUM(M35:P35) -> 270000 | R35: No | X35: Prescott DAF - Northern Trust | Y35: Unrestricted | Z35: Sarah Mitchell | AA35: 11/01/2025 | AB35: Phone call | AC35: ED personal outreach call | AD35: 04/10/2026 | AE35: No | AF35: Yes (Former) | AG35: 0 | AH35: A ($1M+) | AI35: Medium | AJ35: 8 | AK35: Declined from $120K to $50K in FY2025, then lapsed. Former advisory council. Personal call from ED needed. | AL35: Lisa
A36: F-035 | B36: Tomoko Nakamura | C36: Nakamura Design Studio | D36: Corporate | E36: Re-engagement | F36: Lapsed | G36: tnakamura@nakamuradesign.com | H36: (503) 555-2233 | I36: Pacific NW | J36: Entry | K36: 08/01/2022 | L36: 10000 | M36: 10000 | N36: 15000 | O36: 10000 | P36: 0 | Q36: =SUM(M36:P36) -> 35000 | R36: No | X36: Direct | Y36: Unrestricted | Z36: Maria Lopez | AA36: 09/15/2025 | AB36: Email (no response) | AC36: Send personalized project update | AD36: 04/15/2026 | AE36: No | AF36: No | AG36: 0 | AH36: C ($100K-$500K) | AI36: Low | AJ36: 5 | AK36: Portland designer. Gave 3 years. No response to renewal. Try project-specific appeal. | AL36: Rafaela
A37: F-036 | B37: Robert & Christine Andersen | C37: Andersen Family Fund | D37: Individual/Family | E37: Re-engagement | F37: Lapsed | G37: randersen@andersenfund.org | H37: (952) 555-8811 | I37: Midwest | J37: Mid-Level | K37: 05/15/2019 | L37: 30000 | M37: 40000 | N37: 50000 | O37: 0 | P37: 0 | Q37: =SUM(M37:P37) -> 90000 | R37: No | X37: Andersen DAF - Schwab | Y37: Pell-Eligible Scholarships | Z37: James Wright | AA37: 10/20/2025 | AB37: Phone call (voicemail) | AC37: Handwritten note from scholarship recipient | AD37: 04/20/2026 | AE37: No | AF37: No | AG37: 0 | AH37: B ($500K-$1M) | AI37: Medium | AJ37: 7 | AK37: Minneapolis family. Cared about Pell students. Missed FY2025. Try scholarship recipient story. | AL37: Lisa
A38: F-037 | B38: Martin & Louise Kessler | C38: Kessler Group | D38: Corporate | E38: Closed - Declined | F38: Inactive | G38: mkessler@kesslergroup.com | H38: (212) 555-0099 | I38: Northeast | J38: None | M38: 0 | N38: 0 | O38: 0 | P38: 0 | Q38: =SUM(M38:P38) -> 0 | R38: No | Z38: James Wright | AA38: 06/01/2025 | AB38: In-person meeting | AC38: Revisit in 2027 | AD38: 01/15/2027 | AE38: No | AF38: No | AG38: 0 | AH38: A ($1M+) | AI38: Very Low | AJ38: 6 | AK38: Declined. Company restructuring. Said to revisit in 2 years. | AL38: Jack
A39: F-038 | B39: Diane Zhao | C39: Zhao Capital Management | D39: Corporate | E39: Closed - Declined | F39: Inactive | G39: dzhao@zhaocapital.com | H39: (646) 555-3388 | I39: Northeast | J39: None | M39: 0 | N39: 0 | O39: 0 | P39: 0 | Q39: =SUM(M39:P39) -> 0 | R39: No | Z39: Sarah Mitchell | AA39: 08/15/2025 | AB39: Email | AC39: Add to newsletter; passive cultivation | AD39: 08/15/2026 | AE39: No | AF39: No | AG39: 1 | AH39: B ($500K-$1M) | AI39: Very Low | AJ39: 5 | AK39: Politely declined. Prefers arts funding. Keep on radar for arts-STEM if program launches. | AL39: Lisa
A40: F-039 | B40: Jonathan & Claire Harrington | C40: Harrington Charitable Trust | D40: Individual/Family | E40: Stewardship | F40: Active | G40: jharrington@harringtontrust.org | H40: (617) 555-8834 | I40: Northeast | J40: Major | K40: 05/20/2018 | L40: 60000 | M40: 80000 | N40: 90000 | O40: 100000 | P40: 110000 | Q40: =SUM(M40:P40) -> 380000 | R40: Yes | S40: 550000 | T40: FY2025 | U40: FY2029 | V40: 2 of 5 | W40: 110000 | X40: Harrington DAF - Fidelity | Y40: First-Generation Students | Z40: Sarah Mitchell | AA40: 03/01/2026 | AB40: In-person meeting | AC40: Annual pledge check-in | AD40: 05/20/2026 | AE40: No | AF40: Yes | AG40: 3 | AH40: A ($1M+) | AI40: High | AJ40: 9 | AK40: Boston-based. Advisory council. Strong advocates. Host annual donor dinner. | AL40: Jack
A41: F-040 | B41: Lena Volkov | C41: Volkov Tech Foundation | D41: Foundation | E41: Stewardship | F41: Active | G41: lvolkov@volkovtech.org | H41: (408) 555-1199 | I41: West Coast | J41: Mid-Level | K41: 01/15/2023 | L41: 25000 | M41: 0 | N41: 0 | O41: 25000 | P41: 40000 | Q41: =SUM(M41:P41) -> 65000 | R41: No | X41: Direct | Y41: STEM Education | Z41: Maria Lopez | AA41: 02/15/2026 | AB41: Email | AC41: Share program outcomes report | AD41: 04/20/2026 | AE41: No | AF41: No | AG41: 1 | AH41: C ($100K-$500K) | AI41: High | AJ41: 7 | AK41: Silicon Valley tech exec. Doubling down on STEM. Potential for corporate partnership. | AL41: Rafaela
A42: F-041 | B42: Oscar & Valentina Cruz | C42: Cruz Community Fund | D42: Individual/Family | E42: Stewardship | F42: Active | G42: ocruz@cruzfund.org | H42: (213) 555-7766 | I42: West Coast | J42: Mid-Level | K42: 08/01/2020 | L42: 20000 | M42: 25000 | N42: 30000 | O42: 35000 | P42: 45000 | Q42: =SUM(M42:P42) -> 135000 | R42: No | X42: Cruz DAF - Schwab | Y42: Rural Program | Z42: Maria Lopez | AA42: 01/20/2026 | AB42: Phone call | AC42: Invite to rural site visit | AD42: 05/15/2026 | AE42: No | AF42: No | AG42: 2 | AH42: C ($100K-$500K) | AI42: High | AJ42: 7 | AK42: LA-based. Consistent growth. Passionate about rural access. | AL42: Rafaela
A43: F-042 | B43: Sebastian Reeves | C43: Reeves Holdings International | D43: Corporate | E43: Cultivation | F43: Active | G43: sreeves@reevesholdings.com | H43: (305) 555-4488 | I43: Southeast | J43: Mid-Level | K43: 09/01/2024 | L43: 30000 | M43: 0 | N43: 0 | O43: 0 | P43: 30000 | Q43: =SUM(M43:P43) -> 30000 | R43: No | X43: Direct | Y43: Northeast Programs | Z43: James Wright | AA43: 03/05/2026 | AB43: In-person meeting | AC43: Discuss multi-year partnership | AD43: 05/01/2026 | AE43: No | AF43: No | AG43: 1 | AH43: B ($500K-$1M) | AI43: Medium | AJ43: 7 | AK43: Miami-based. International holdings. Second gift expected Q2. | AL43: Jack
A44: F-043 | B44: Miriam Goldstein-Levy | C44: Goldstein-Levy Philanthropic Fund | D44: Individual/Family | E44: Stewardship | F44: Active | G44: mgoldstein@glfund.org | H44: (212) 555-5544 | I44: Northeast | J44: Major | K44: 11/15/2017 | L44: 75000 | M44: 90000 | N44: 100000 | O44: 110000 | P44: 120000 | Q44: =SUM(M44:P44) -> 420000 | R44: Yes | S44: 600000 | T44: FY2024 | U44: FY2028 | V44: 3 of 5 | W44: 120000 | X44: Goldstein-Levy DAF - Goldman Sachs | Y44: Scholarship Endowment | Z44: Sarah Mitchell | AA44: 03/18/2026 | AB44: Phone call | AC44: Endowment naming discussion | AD44: 04/30/2026 | AE44: No | AF44: No | AG44: 2 | AH44: A ($1M+) | AI44: Very High | AJ44: 10 | AK44: NYC philanthropist. Interested in naming a scholarship endowment. High-touch stewardship needed. | AL44: Jack
A45: F-044 | B45: Derek & Monique Baptiste | C45: Baptiste Family Foundation | D45: Foundation | E45: Stewardship | F45: Active | G45: dbaptiste@baptistefdn.org | H45: (786) 555-3300 | I45: Southeast | J45: Mid-Level | K45: 03/15/2022 | L45: 20000 | M45: 20000 | N45: 30000 | O45: 35000 | P45: 45000 | Q45: =SUM(M45:P45) -> 130000 | R45: No | X45: Direct | Y45: Pell-Eligible Students | Z45: Maria Lopez | AA45: 02/28/2026 | AB45: Email | AC45: Connect with Novak re: Pell focus | AD45: 04/15/2026 | AE45: No | AF45: No | AG45: 1 | AH45: C ($100K-$500K) | AI45: High | AJ45: 7 | AK45: Miami. Haitian-American family. Strong Pell focus. Could partner with Novak Foundation. | AL45: Rafaela
A46: F-045 | B46: Elizabeth Hawthorne | C46: Hawthorne Media Corp | D46: Corporate | E46: Stewardship | F46: Active | G46: ehawthorne@hawthornecorp.com | H46: (310) 555-2277 | I46: West Coast | J46: Entry | K46: 06/01/2024 | L46: 15000 | M46: 0 | N46: 0 | O46: 0 | P46: 15000 | Q46: =SUM(M46:P46) -> 15000 | R46: No | X46: Direct | Y46: Unrestricted | Z46: Sarah Mitchell | AA46: 12/01/2025 | AB46: Event follow-up | AC46: Invite to Q2 donor event | AD46: 05/01/2026 | AE46: No | AF46: No | AG46: 1 | AH46: B ($500K-$1M) | AI46: Low | AJ46: 6 | AK46: Media exec. Initial gift at gala. High capacity but early stage. | AL46: Rafaela
A47: F-046 | B47: Andrew & Susan Pemberton | C47: Pemberton Investments | D47: Corporate | E47: Identification | F47: Prospect | G47: apemberton@pembertoninvest.com | H47: (704) 555-9977 | I47: Southeast | J47: None | M47: 0 | N47: 0 | O47: 0 | P47: 0 | Q47: =SUM(M47:P47) -> 0 | R47: No | Z47: James Wright | AA47: 02/20/2026 | AB47: Research | AC47: Cold outreach via annual appeal | AD47: 05/01/2026 | AE47: No | AF47: No | AG47: 0 | AH47: A ($1M+) | AI47: Very Low | AJ47: 6 | AK47: Charlotte PE firm. Education giving in other contexts. Peer-screened. | AL47: Jack
A48: F-047 | B48: Maya Singh-Patel | C48: Singh-Patel Ventures | D48: Corporate | E48: Cultivation | F48: Prospect | G48: msingh@singhpatelvc.com | H48: (415) 555-6688 | I48: West Coast | J48: Entry | K48: 01/30/2026 | L48: 10000 | M48: 0 | N48: 0 | O48: 0 | P48: 10000 | Q48: =SUM(M48:P48) -> 10000 | R48: No | X48: Direct | Y48: STEM Education | Z48: Maria Lopez | AA48: 01/30/2026 | AB48: Event follow-up | AC48: Coffee meeting to learn interests | AD48: 04/20/2026 | AE48: No | AF48: No | AG48: 1 | AH48: C ($100K-$500K) | AI48: Medium | AJ48: 6 | AK48: SF VC partner. Initial gift at winter event. STEM aligned. Early cultivation. | AL48: Rafaela
A49: F-048 | B49: Raymond & Barbara O'Sullivan | C49: O'Sullivan Family Foundation | D49: Foundation | E49: Solicitation | F49: Prospect | G49: rosullivan@osullivanfdn.org | H49: (312) 555-5500 | I49: Midwest | J49: None | M49: 0 | N49: 0 | O49: 0 | P49: 0 | Q49: =SUM(M49:P49) -> 0 | R49: No | Y49: General Scholarship | Z49: Sarah Mitchell | AA49: 03/28/2026 | AB49: Proposal submitted | AC49: Await response; follow up June | AD49: 06/10/2026 | AE49: No | AF49: No | AG49: 1 | AH49: A ($1M+) | AI49: Medium | AJ49: 8 | AK49: $250K proposal for general scholarship fund. Chicago foundation. Board meets quarterly in June. | AL49: Lisa
A50: F-049 | B50: Ingrid Johansson-Berg | C50: Nordic Education Initiative | D50: Foundation | E50: Qualification | F50: Prospect | G50: ijohansson@nordicedu.org | H50: (612) 555-7700 | I50: Midwest | J50: None | M50: 0 | N50: 0 | O50: 0 | P50: 0 | Q50: =SUM(M50:P50) -> 0 | R50: No | Y50: International Student Support | Z50: James Wright | AA50: 03/15/2026 | AB50: Phone call | AC50: Schedule campus tour for board | AD50: 05/01/2026 | AE50: No | AF50: No | AG50: 0 | AH50: B ($500K-$1M) | AI50: Medium | AJ50: 7 | AK50: Minneapolis-based Nordic foundation. Focus on international education exchange. New prospect. | AL50: Lisa
A51: F-050 | B51: Terrence & Alma Washington-Greene | C51: Washington-Greene Family Trust | D51: Individual/Family | E51: Cultivation | F51: Prospect | G51: twashington@wgfamilytrust.org | H51: (202) 555-1144 | I51: Mid-Atlantic | J51: Entry | K51: 11/01/2025 | L51: 20000 | M51: 0 | N51: 0 | O51: 0 | P51: 20000 | Q51: =SUM(M51:P51) -> 20000 | R51: No | X51: Direct | Y51: Education Equity | Z51: James Wright | AA51: 11/15/2025 | AB51: Event follow-up | AC51: Invite to DC donor circle | AD51: 04/15/2026 | AE51: No | AF51: No | AG51: 1 | AH51: A ($1M+) | AI51: Low | AJ51: 7 | AK51: DC-based. Initial gift at fall event. Known philanthropists in education equity. | AL51: Jack
A52: F-051 | B52: Steven & Marie Lindqvist | C52: Lindqvist Group | D52: Corporate | E52: Re-engagement | F52: Lapsed | G52: slindqvist@lindqvistgroup.com | H52: (206) 555-8800 | I52: Pacific NW | J52: Mid-Level | K52: 02/01/2019 | L52: 25000 | M52: 35000 | N52: 40000 | O52: 25000 | P52: 0 | Q52: =SUM(M52:P52) -> 100000 | R52: No | X52: Direct | Y52: Unrestricted | Z52: Maria Lopez | AA52: 10/15/2025 | AB52: Phone call | AC52: Personal note from ED with program update | AD52: 04/20/2026 | AE52: No | AF52: No | AG52: 0 | AH52: B ($500K-$1M) | AI52: Medium | AJ52: 7 | AK52: Seattle. Declined from $40K to $25K then lapsed. May be tied to company financials. | AL52: Lisa
A53: F-052 | B53: Claudia Ferreira-Santos | C53: Ferreira-Santos Associates | D53: Corporate | E53: Re-engagement | F53: Lapsed | G53: cferreira@fsassociates.com | H53: (617) 555-9933 | I53: Northeast | J53: Entry | K53: 07/01/2021 | L53: 10000 | M53: 10000 | N53: 15000 | O53: 0 | P53: 0 | Q53: =SUM(M53:P53) -> 25000 | R53: No | X53: Direct | Y53: STEM Education | Z53: James Wright | AA53: 09/01/2025 | AB53: Email (no response) | AC53: Try LinkedIn outreach | AD53: 04/15/2026 | AE53: No | AF53: No | AG53: 0 | AH53: C ($100K-$500K) | AI53: Low | AJ53: 5 | AK53: Boston consulting firm. 3-year donor. No response to emails. Try alternative channels. | AL53: Jack
A54: F-053 | B54: Philip & Janet Rothschild-Murray | C54: Rothschild-Murray Trust | D54: Individual/Family | E54: Closed - Declined | F54: Inactive | G54: prothschild@rmtrust.org | H54: (860) 555-2211 | I54: Northeast | J54: None | M54: 0 | N54: 0 | O54: 0 | P54: 0 | Q54: =SUM(M54:P54) -> 0 | R54: No | Z54: Sarah Mitchell | AA54: 07/01/2025 | AB54: Phone call | AC54: Monitor; possible re-approach via Worthington | AD54: 01/15/2027 | AE54: No | AF54: No | AG54: 0 | AH54: A ($1M+) | AI54: Very Low | AJ54: 6 | AK54: Connecticut. Declined due to existing education commitments. Revisit via Worthington intro. | AL54: Jack
A55: F-054 | B55: Grace Okafor-Williams | C55: Okafor-Williams Group | D55: Corporate | E55: Closed - Declined | F55: Inactive | G55: gokafor@owgroup.com | H55: (404) 555-1177 | I55: Southeast | J55: None | M55: 0 | N55: 0 | O55: 0 | P55: 0 | Q55: =SUM(M55:P55) -> 0 | R55: No | Z55: Maria Lopez | AA55: 05/15/2025 | AB55: In-person meeting | AC55: Revisit if arts-STEM program launches | AD55: 09/01/2026 | AE55: No | AF55: No | AG55: 1 | AH55: B ($500K-$1M) | AI55: Very Low | AJ55: 5 | AK55: Atlanta. Prefers arts-focused philanthropy. Could revisit if arts-STEM integration launches. | AL55: Lisa
A56: F-055 | B56: Dr. Samuel Adeyemi | C56: Adeyemi Health Sciences Trust | D56: Foundation | E56: Identification | F56: Prospect | G56: sadeyemi@adeyemitrust.org | H56: (713) 555-0011 | I56: Southwest | J56: None | M56: 0 | N56: 0 | O56: 0 | P56: 0 | Q56: =SUM(M56:P56) -> 0 | R56: No | Y56: Health Sciences | Z56: Maria Lopez | AA56: 03/01/2026 | AB56: Research | AC56: Request intro through Vasquez-Torres | AD56: 04/30/2026 | AE56: No | AF56: No | AG56: 0 | AH56: B ($500K-$1M) | AI56: Low | AJ56: 6 | AK56: Houston physician-philanthropist. Health education focus. Connected to Vasquez-Torres network. | AL56: Rafaela
A57: F-056 | B57: Jessica & Ryan Calloway | C57: Calloway Ventures | D57: Corporate | E57: Identification | F57: Prospect | G57: jcalloway@callowayvc.com | H57: (512) 555-2299 | I57: Southwest | J57: None | M57: 0 | N57: 0 | O57: 0 | P57: 0 | Q57: =SUM(M57:P57) -> 0 | R57: No | Z57: James Wright | AA57: 02/15/2026 | AB57: Research | AC57: Add to Austin donor event invite | AD57: 05/01/2026 | AE57: No | AF57: No | AG57: 0 | AH57: A ($1M+) | AI57: Very Low | AJ57: 6 | AK57: Austin VC firm. IPO exit 2025. No philanthropic history identified yet. Peer-screened. | AL57: Lisa
A58: F-057 | B58: Nadine Brosseau | C58: Brosseau Family Fund | D58: Individual/Family | E58: Qualification | F58: Prospect | G58: nbrosseau@brosseaufund.org | H58: (504) 555-6633 | I58: Southeast | J58: None | M58: 0 | N58: 0 | O58: 0 | P58: 0 | Q58: =SUM(M58:P58) -> 0 | R58: No | Y58: Education Equity | Z58: Sarah Mitchell | AA58: 03/10/2026 | AB58: Phone call | AC58: Schedule intro lunch | AD58: 04/20/2026 | AE58: No | AF58: No | AG58: 0 | AH58: B ($500K-$1M) | AI58: Medium | AJ58: 7 | AK58: New Orleans family wealth. Education equity interest. Warm lead from Moreau. | AL58: Jack
A59: F-058 | B59: Timothy & Andrea Park-Saunders | C59: Park-Saunders Foundation | D59: Foundation | E59: Cultivation | F59: Prospect | G59: tpark@parksaundersfdn.org | H59: (206) 555-8877 | I59: Pacific NW | J59: Entry | K59: 02/01/2026 | L59: 10000 | M59: 0 | N59: 0 | O59: 0 | P59: 10000 | Q59: =SUM(M59:P59) -> 10000 | R59: No | X59: Direct | Y59: Rural Program | Z59: Maria Lopez | AA59: 02/01/2026 | AB59: Event follow-up | AC59: Thank you call + site visit invite | AD59: 04/15/2026 | AE59: No | AF59: No | AG59: 1 | AH59: B ($500K-$1M) | AI59: Medium | AJ59: 7 | AK59: Seattle foundation. Initial gift at winter gala. Rural education aligned. | AL59: Rafaela
A60: F-059 | B60: Cynthia Abrams-Klein | C60: Abrams-Klein Charitable Trust | D60: Individual/Family | E60: Solicitation | F60: Prospect | G60: cabrams@akcharitable.org | H60: (212) 555-4400 | I60: Northeast | J60: None | M60: 0 | N60: 0 | O60: 0 | P60: 0 | Q60: =SUM(M60:P60) -> 0 | R60: No | Y60: Scholarship Endowment | Z60: Sarah Mitchell | AA60: 03/25/2026 | AB60: Proposal submitted | AC60: Follow up post-review in May | AD60: 05/15/2026 | AE60: No | AF60: No | AG60: 2 | AH60: A ($1M+) | AI60: High | AJ60: 9 | AK60: $300K endowment proposal. NYC philanthropist. Multiple cultivation meetings completed. Strong alignment. | AL60: Jack
A61: F-060 | B61: Marcus Jennings | C61: Jennings Capital Group | D61: Corporate | E61: Identification | F61: Prospect | G61: mjennings@jenningscapital.com | H61: (704) 555-3355 | I61: Southeast | J61: None | M61: 0 | N61: 0 | O61: 0 | P61: 0 | Q61: =SUM(M61:P61) -> 0 | R61: No | Z61: James Wright | AA61: 01/15/2026 | AB61: Research | AC61: Peer screening complete; request intro via Stratton | AD61: 04/30/2026 | AE61: No | AF61: No | AG61: 0 | AH61: A ($1M+) | AI61: Low | AJ61: 7 | AK61: Charlotte finance. Peer-screened. Education history on other boards. Stratton connection. | AL61: Lisa
A62: F-061 | B62: Dr. Wei & Jennifer Liu-Chang | C62: Liu-Chang Education Foundation | D62: Foundation | E62: Cultivation | F62: Prospect | G62: wliu@liuchangfdn.org | H62: (650) 555-1177 | I62: West Coast | J62: Entry | K62: 11/15/2025 | L62: 25000 | M62: 0 | N62: 0 | O62: 0 | P62: 25000 | Q62: =SUM(M62:P62) -> 25000 | R62: No | X62: Direct | Y62: STEM Education | Z62: Maria Lopez | AA62: 01/15/2026 | AB62: In-person meeting | AC62: Submit LOI for STEM grant | AD62: 04/15/2026 | AE62: No | AF62: No | AG62: 1 | AH62: A ($1M+) | AI62: Medium | AJ62: 8 | AK62: Palo Alto. Tech fortune. $25K initial gift. Foundation has $50M+ in assets. High potential. | AL62: Rafaela
A63: F-062 | B63: Natasha Orlova-Petrov | C63: Orlova-Petrov Arts & Sciences Fund | D63: Foundation | E63: Qualification | F63: Prospect | G63: norlova@opfund.org | H63: (312) 555-6622 | I63: Midwest | J63: None | M63: 0 | N63: 0 | O63: 0 | P63: 0 | Q63: =SUM(M63:P63) -> 0 | R63: No | Y63: Arts-STEM Integration | Z63: James Wright | AA63: 02/28/2026 | AB63: Phone call | AC63: Explore arts-STEM alignment | AD63: 04/25/2026 | AE63: No | AF63: No | AG63: 0 | AH63: B ($500K-$1M) | AI63: Medium | AJ63: 7 | AK63: Chicago. Arts + sciences intersection. Could be perfect fit if arts-STEM program launches. | AL63: Jack
A64: F-063 | B64: Brandon & Tiffany Maxwell | C64: Maxwell Legacy Foundation | D64: Foundation | E64: Cultivation | F64: Prospect | G64: bmaxwell@maxwelllegacy.org | H64: (404) 555-9944 | I64: Southeast | J64: Entry | K64: 12/01/2025 | L64: 20000 | M64: 0 | N64: 0 | O64: 0 | P64: 20000 | Q64: =SUM(M64:P64) -> 20000 | R64: No | X64: Direct | Y64: First-Generation Students | Z64: Maria Lopez | AA64: 12/15/2025 | AB64: Event follow-up | AC64: Campus visit + scholar meeting | AD64: 05/01/2026 | AE64: No | AF64: No | AG64: 1 | AH64: B ($500K-$1M) | AI64: Medium | AJ64: 7 | AK64: Atlanta. Both first-gen college. Deep personal connection to mission. $20K initial gift promising. | AL64: Lisa
A65: F-064 | B65: Eleanor Whitmore-Davis | C65: Whitmore-Davis Trust | D65: Individual/Family | E65: Solicitation | F65: Prospect | G65: ewhitmore@wdtrust.org | H65: (860) 555-7788 | I65: Northeast | J65: None | M65: 0 | N65: 0 | O65: 0 | P65: 0 | Q65: =SUM(M65:P65) -> 0 | R65: No | Y65: Unrestricted Endowment | Z65: Sarah Mitchell | AA65: 03/20/2026 | AB65: Proposal submitted | AC65: Board review in June | AD65: 06/15/2026 | AE65: No | AF65: No | AG65: 2 | AH65: A ($1M+) | AI65: Medium | AJ65: 8 | AK65: $500K unrestricted endowment proposal. Connecticut. Worthington referral. Long cultivation cycle. | AL65: Jack
A66: F-065 | B66: Roberto & Ana Castillo-Vega | C66: Castillo-Vega Enterprises | D66: Corporate | E66: Identification | F66: Prospect | G66: rcastillo@cventerprises.com | H66: (210) 555-5588 | I66: Southwest | J66: None | M66: 0 | N66: 0 | O66: 0 | P66: 0 | Q66: =SUM(M66:P66) -> 0 | R66: No | Z66: Maria Lopez | AA66: 02/01/2026 | AB66: Research | AC66: Outreach at San Antonio business leaders event | AD66: 05/15/2026 | AE66: No | AF66: No | AG66: 0 | AH66: C ($100K-$500K) | AI66: Low | AJ66: 5 | AK66: San Antonio manufacturing. Hispanic business leader. Education philanthropy unknown. Cold prospect. | AL66: Lisa
A67: F-066 | B67: Dr. Priscilla Oduya | C67: Oduya Global Education Fund | D67: Foundation | E67: Qualification | F67: Prospect | G67: poduya@oduyafund.org | H67: (202) 555-3366 | I67: Mid-Atlantic | J67: None | M67: 0 | N67: 0 | O67: 0 | P67: 0 | Q67: =SUM(M67:P67) -> 0 | R67: No | Y67: International Student Scholarships | Z67: James Wright | AA67: 03/15/2026 | AB67: Phone call | AC67: Explore international scholarship alignment | AD67: 04/30/2026 | AE67: No | AF67: No | AG67: 0 | AH67: B ($500K-$1M) | AI67: Medium | AJ67: 7 | AK67: DC-based global education fund. Focus on African diaspora students. New contact via conference. | AL67: Jack
A68: F-067 | B68: Alan & Deborah Sinclair | C68: Sinclair Timber Company | D68: Corporate | E68: Cultivation | F68: Prospect | G68: asinclair@sinclairtimber.com | H68: (503) 555-1155 | I68: Pacific NW | J68: Entry | K68: 01/15/2026 | L68: 15000 | M68: 0 | N68: 0 | O68: 0 | P68: 15000 | Q68: =SUM(M68:P68) -> 15000 | R68: No | X68: Direct | Y68: Rural Program | Z68: Maria Lopez | AA68: 01/20/2026 | AB68: Phone call | AC68: Site visit to rural program in Oregon | AD68: 05/01/2026 | AE68: No | AF68: No | AG68: 1 | AH68: C ($100K-$500K) | AI68: Medium | AJ68: 6 | AK68: Portland timber company. Rural communities connection. $15K at winter event. Very aligned with rural program. | AL68: Lisa
A69: F-068 | B69: Vanessa & Michael Torres-Rubin | C69: Torres-Rubin Family Fund | D69: Individual/Family | E69: Identification | F69: Prospect | G69: vtorres@trfamilyfund.org | H69: (305) 555-8844 | I69: Southeast | J69: None | M69: 0 | N69: 0 | O69: 0 | P69: 0 | Q69: =SUM(M69:P69) -> 0 | R69: No | Z69: James Wright | AA69: 03/01/2026 | AB69: Research | AC69: Annual appeal mailing + gala invite | AD69: 05/01/2026 | AE69: No | AF69: No | AG69: 0 | AH69: C ($100K-$500K) | AI69: Low | AJ69: 5 | AK69: Miami family fund. Identified through Baptiste network. Education giving elsewhere. | AL69: Jack
A70: F-069 | B70: Christine Yamamoto | C70: Yamamoto Tech Ventures | D70: Corporate | E70: Cultivation | F70: Prospect | G70: cyamamoto@yamatech.com | H70: (408) 555-3377 | I70: West Coast | J70: Entry | K70: 02/15/2026 | L70: 10000 | M70: 0 | N70: 0 | O70: 0 | P70: 10000 | Q70: =SUM(M70:P70) -> 10000 | R70: No | X70: Direct | Y70: STEM Education | Z70: Maria Lopez | AA70: 02/20/2026 | AB70: Email | AC70: Share STEM program outcomes deck | AD70: 04/15/2026 | AE70: No | AF70: No | AG70: 1 | AH70: C ($100K-$500K) | AI70: Medium | AJ70: 6 | AK70: San Jose. Tech exec. Initial gift online. Follow up with personal outreach. | AL70: Rafaela
A71: F-070 | B71: Edward & Margaret Blackstone | C71: Blackstone Heritage Foundation | D71: Foundation | E71: Solicitation | F71: Prospect | G71: eblackstone@blackstonehf.org | H71: (617) 555-4422 | I71: Northeast | J71: None | M71: 0 | N71: 0 | O71: 0 | P71: 0 | Q71: =SUM(M71:P71) -> 0 | R71: No | Y71: General Scholarship | Z71: Sarah Mitchell | AA71: 03/30/2026 | AB71: Proposal submitted | AC71: Await foundation decision in July | AD71: 07/01/2026 | AE71: No | AF71: No | AG71: 1 | AH71: A ($1M+) | AI71: Medium | AJ71: 8 | AK71: $400K scholarship proposal. Boston heritage foundation. Slow-moving board. Dubois provided introduction. | AL71: Lisa
A72: F-071 | B72: Patricia Nguyen-Thompson | C72: Nguyen-Thompson Associates | D72: Corporate | E72: Qualification | F72: Prospect | G72: pnguyen@ntassociates.com | H72: (714) 555-9900 | I72: West Coast | J72: None | M72: 0 | N72: 0 | O72: 0 | P72: 0 | Q72: =SUM(M72:P72) -> 0 | R72: No | Y72: STEM Education | Z72: Maria Lopez | AA72: 03/20/2026 | AB72: Phone call | AC72: Intro meeting scheduled | AD72: 04/22/2026 | AE72: No | AF72: No | AG72: 0 | AH72: C ($100K-$500K) | AI72: Medium | AJ72: 6 | AK72: Orange County consulting. Anh Nguyen (scholarship alum) works there. Organic connection. | AL72: Rafaela
A73: F-072 | B73: Dmitri & Svetlana Ivanov | C73: Ivanov Family Trust | D73: Individual/Family | E73: Identification | F73: Prospect | G73: divanov@ivanovtrust.com | H73: (646) 555-7711 | I73: Northeast | J73: None | M73: 0 | N73: 0 | O73: 0 | P73: 0 | Q73: =SUM(M73:P73) -> 0 | R73: No | Z73: James Wright | AA73: 02/10/2026 | AB73: Research | AC73: Cold outreach via annual appeal | AD73: 05/01/2026 | AE73: No | AF73: No | AG73: 0 | AH73: A ($1M+) | AI73: Very Low | AJ73: 6 | AK73: NYC finance family. Wealth screening flagged. No known education philanthropy. Very early stage. | AL73: Jack
A74: F-073 | B74: Monique St. Claire | C74: St. Claire Education Partners | D74: Corporate | E74: Cultivation | F74: Prospect | G74: mstclaire@stclaireedu.com | H74: (504) 555-2244 | I74: Southeast | J74: Entry | K74: 01/30/2026 | L74: 10000 | M74: 0 | N74: 0 | O74: 0 | P74: 10000 | Q74: =SUM(M74:P74) -> 10000 | R74: No | X74: Direct | Y74: Education Equity | Z74: Maria Lopez | AA74: 02/05/2026 | AB74: Event follow-up | AC74: Coffee meeting in New Orleans | AD74: 04/15/2026 | AE74: No | AF74: No | AG74: 1 | AH74: C ($100K-$500K) | AI74: Medium | AJ74: 6 | AK74: NOLA education consulting firm. $10K at winter event. Mission-aligned business. | AL74: Jack
A75: F-074 | B75: Daniel & Rebecca Hoffman | C75: Hoffman Associates | D75: Corporate | E75: Stewardship | F75: Active | G75: dhoffman@hoffmanassoc.com | H75: (312) 555-0044 | I75: Midwest | J75: Entry | K75: 09/01/2023 | L75: 10000 | M75: 0 | N75: 0 | O75: 10000 | P75: 15000 | Q75: =SUM(M75:P75) -> 25000 | R75: No | X75: Direct | Y75: Unrestricted | Z75: James Wright | AA75: 12/01/2025 | AB75: Holiday card + call | AC75: Upgrade ask at spring event | AD75: 05/15/2026 | AE75: No | AF75: No | AG75: 1 | AH75: C ($100K-$500K) | AI75: Medium | AJ75: 6 | AK75: Chicago consulting. Year 3. Slow but steady growth. | AL75: Lisa
A76: F-075 | B76: Lucia Mendoza-Garcia | C76: Mendoza-Garcia Foundation | D76: Foundation | E76: Stewardship | F76: Active | G76: lmendoza@mgfoundation.org | H76: (213) 555-8833 | I76: West Coast | J76: Mid-Level | K76: 04/01/2021 | L76: 20000 | M76: 25000 | N76: 30000 | O76: 35000 | P76: 50000 | Q76: =SUM(M76:P76) -> 140000 | R76: No | X76: Mendoza-Garcia DAF - Schwab | Y76: First-Generation Students | Z76: Maria Lopez | AA76: 03/10/2026 | AB76: Phone call | AC76: Propose multi-year commitment | AD76: 05/01/2026 | AE76: No | AF76: No | AG76: 2 | AH76: C ($100K-$500K) | AI76: High | AJ76: 7 | AK76: LA-based. First-gen focus. Consistent growth. Ready for multi-year conversation. | AL76: Rafaela
A77: F-076 | B77: Warren & Doris Carmichael | C77: Carmichael Trust | D77: Individual/Family | E77: Re-engagement | F77: Lapsed | G77: wcarmichael@carmichaeltrust.org | H77: (847) 555-6699 | I77: Midwest | J77: Mid-Level | K77: 01/15/2018 | L77: 30000 | M77: 35000 | N77: 40000 | O77: 20000 | P77: 0 | Q77: =SUM(M77:P77) -> 95000 | R77: No | X77: Carmichael DAF - Vanguard | Y77: Unrestricted | Z77: Sarah Mitchell | AA77: 11/01/2025 | AB77: Phone call | AC77: ED personal call + handwritten note | AD77: 04/15/2026 | AE77: No | AF77: Yes (Former) | AG77: 0 | AH77: B ($500K-$1M) | AI77: Medium | AJ77: 7 | AK77: Evanston IL. Declined sharply then lapsed. Former advisory council. Health issues may be factor; handle sensitively. | AL77: Lisa
A78: F-077 | B78: Jacqueline DuPont-Williams | C78: DuPont-Williams Group | D78: Corporate | E78: Re-engagement | F78: Lapsed | G78: jdupont@dpwgroup.com | H78: (202) 555-7744 | I78: Mid-Atlantic | J78: Entry | K78: 06/01/2022 | L78: 10000 | M78: 10000 | N78: 15000 | O78: 0 | P78: 0 | Q78: =SUM(M78:P78) -> 25000 | R78: No | X78: Direct | Y78: Unrestricted | Z78: James Wright | AA78: 10/01/2025 | AB78: Email (no response) | AC78: LinkedIn message + personal note | AD78: 04/20/2026 | AE78: No | AF78: No | AG78: 0 | AH78: C ($100K-$500K) | AI78: Low | AJ78: 5 | AK78: DC consulting. 3-year donor. Company may have downsized. Try personal channel. | AL78: Jack
A79: F-078 | B79: Gordon & Lillian Ashworth | C79: Ashworth Family Trust | D79: Individual/Family | E79: Closed - Declined | F79: Inactive | G79: gashworth@ashworthtrust.org | H79: (203) 555-0022 | I79: Northeast | J79: None | M79: 0 | N79: 0 | O79: 0 | P79: 0 | Q79: =SUM(M79:P79) -> 0 | R79: No | Z79: Sarah Mitchell | AA79: 04/01/2025 | AB79: Phone call | AC79: Long-term monitor; possible estate gift prospect | AD79: 01/01/2027 | AE79: No | AF79: No | AG79: 0 | AH79: A ($1M+) | AI79: Very Low | AJ79: 6 | AK79: Greenwich CT. Declined politely. Mentioned us in estate planning conversations per advisor. Very long-term. | AL79: Jack
A80: F-079 | B80: Reginald Barnes | C80: Barnes Logistics Corp | D80: Corporate | E80: Closed - Declined | F80: Inactive | G80: rbarnes@barneslogistics.com | H80: (773) 555-5566 | I80: Midwest | J80: None | M80: 0 | N80: 0 | O80: 0 | P80: 0 | Q80: =SUM(M80:P80) -> 0 | R80: No | Z80: James Wright | AA80: 07/15/2025 | AB80: Email | AC80: Annual newsletter only | AD80: 07/15/2026 | AE80: No | AF80: No | AG80: 0 | AH80: C ($100K-$500K) | AI80: Very Low | AJ80: 4 | AK80: Chicago logistics. Declined. Budget constraints. Keep on newsletter. | AL80: Jack
A81: F-080 | B81: Katherine & Paul Remington-Hall | C81: Remington-Hall Charitable Fund | D81: Individual/Family | E81: Closed - Declined | F81: Inactive | G81: kremington@rhfund.org | H81: (860) 555-1188 | I81: Northeast | J81: None | M81: 0 | N81: 0 | O81: 0 | P81: 0 | Q81: =SUM(M81:P81) -> 0 | R81: No | Z81: Sarah Mitchell | AA81: 05/01/2025 | AB81: In-person meeting | AC81: Revisit when arts-STEM launches | AD81: 09/01/2026 | AE81: No | AF81: No | AG81: 1 | AH81: A ($1M+) | AI81: Very Low | AJ81: 6 | AK81: Connecticut. Arts-focused. Declined because no arts component. Could revisit with arts-STEM program. | AL81: Jack

Sheet Funder Database March
A1: Funder ID | B1: Donor Name | C1: Organization | D1: Donor Type | E1: Stage | F1: Status | G1: Primary Contact Email | H1: Phone | I1: Region | J1: Giving Level | K1: First Gift Date | L1: First Gift Amount | M1: FY2023 Giving | N1: FY2024 Giving | O1: FY2025 Giving | P1: FY2026 Giving (YTD) | Q1: Lifetime Giving | R1: Multi-Year Pledge? | S1: Pledge Total | T1: Pledge Start FY | U1: Pledge End FY | V1: Current Pledge Year | W1: Annual Pledge Amount | X1: Fund / DAF | Y1: Gift Designation | Z1: Stewardship Owner | AA1: Last Contact Date | AB1: Last Contact Type | AC1: Next Action | AD1: Next Action Date | AE1: Board Member? | AF1: Advisory Council? | AG1: Event Attendance (Last 12mo) | AH1: Capacity Rating | AI1: Likelihood Rating | AJ1: Priority Score | AK1: Notes | AL1: Account Owner
A2: F-001 | B2: David & Rachel Kim | C2: Kim Family Trust | D2: Individual/Family | E2: Solicitation | F2: Active | G2: david.kim@kimfamilytrust.org | H2: (310) 555-6243 | I2: West Coast | J2: Transformational | K2: 03/15/2016 | L2: 100000 | M2: 350000 | N2: 400000 | O2: 450000 | P2: 341200 | Q2: =SUM(M2:P2) -> 1541200 | R2: Yes | S2: 2500000 | T2: FY2022 | U2: FY2027 | V2: 5 of 6 | W2: 450000 | X2: Kim Family DAF - Goldman Sachs Philanthropy Fund | Y2: Unrestricted / West Coast Initiative | Z2: Sarah Mitchell | AA2: 03/12/2026 | AB2: In-person meeting | AC2: Cultivation event planning at Kim residence | AD2: 05/01/2026 | AE2: No | AF2: No | AG2: 3 | AH2: A ($1M+) | AI2: Very High | AJ2: 8 | AK2: 10-year donor. Interested in West Coast expansion. Rachel hosting May gala cultivation event. | AL2: Lisa
A3: F-002 | B3: Margaret Chen | C3: Chen Family Foundation | D3: Foundation | E3: Stewardship | F3: Active | G3: margaret.chen@chenfamilyfdn.org | H3: (415) 555-2891 | I3: West Coast | J3: Major | K3: 09/20/2019 | L3: 50000 | M3: 150000 | N3: 200000 | O3: 250000 | P3: 166900 | Q3: =SUM(M3:P3) -> 766900 | R3: Yes | S3: 1250000 | T3: FY2024 | U3: FY2028 | V3: 3 of 5 | W3: 250000 | X3: Chen Family DAF - Fidelity Charitable | Y3: STEM Education | Z3: Sarah Mitchell | AA3: 02/28/2026 | AB3: Phone call | AC3: Finalize advisory board invitation | AD3: 04/15/2026 | AE3: No | AF3: Pending | AG3: 2 | AH3: A ($1M+) | AI3: High | AJ3: 9 | AK3: Connected us with Priya Ramanathan. Interested in advisory board. | AL3: Rafaela
A4: F-003 | B4: Alicia Gutierrez-Santos | C4: Santos Foundation | D4: Foundation | E4: Stewardship | F4: Active | G4: alicia@santosfoundation.org | H4: (713) 555-3476 | I4: Southwest | J4: Major | K4: 06/10/2021 | L4: 75000 | M4: 100000 | N4: 120000 | O4: 150000 | P4: 122000 | Q4: =SUM(M4:P4) -> 492000 | R4: Yes | S4: 900000 | T4: FY2024 | U4: FY2028 | V4: 3 of 5 | W4: 180000 | X4: Santos Foundation DAF - National Philanthropic Trust | Y4: STEM Education Pipeline | Z4: Maria Lopez | AA4: 03/05/2026 | AB4: Email | AC4: Coordinate joint site visit with Sandra Okonkwo | AD4: 04/20/2026 | AE4: No | AF4: No | AG4: 2 | AH4: B ($500K-$1M) | AI4: Very High | AJ4: 9 | AK4: Earmarked for STEM pipeline. Wants quarterly impact reports. Suggested joint site visit with Okonkwo. | AL4: Jack
A5: F-004 | B5: Robert Blackwell III | C5: Blackwell Industries | D5: Corporate | E5: Cultivation | F5: Active | G5: r.blackwell@blackwellindustries.com | H5: (212) 555-7634 | I5: Northeast | J5: Major | K5: 01/22/2026 | L5: 150000 | M5: 0 | N5: 0 | O5: 0 | P5: 118900 | Q5: =SUM(M5:P5) -> 118900 | R5: No | X5: Blackwell Giving Fund - Schwab Charitable | Y5: Northeast Programs | Z5: James Wright | AA5: 02/15/2026 | AB5: In-person meeting | AC5: Prepare cultivation strategy | AD5: 04/30/2026 | AE5: No | AF5: No | AG5: 1 | AH5: A ($1M+) | AI5: Medium | AJ5: 8 | AK5: First-time major donor. Board referral from Thomas Fitzgerald. High capacity prospect. | AL5: Lisa
A6: F-005 | B6: James & Dorothy Whitfield | C6: Whitfield Group | D6: Individual/Family | E6: Stewardship | F6: Active | G6: jwhitfield@whitfieldgroup.net | H6: (312) 555-8819 | I6: Midwest | J6: Major | K6: 11/01/2018 | L6: 50000 | M6: 75000 | N6: 85000 | O6: 100000 | P6: 61400 | Q6: =SUM(M6:P6) -> 321400 | R6: Yes | S6: 500000 | T6: FY2024 | U6: FY2028 | V6: 3 of 5 | W6: 100000 | X6: Whitfield Family DAF - Vanguard Charitable | Y6: Unrestricted | Z6: Sarah Mitchell | AA6: 01/20/2026 | AB6: Holiday card + call | AC6: Annual renewal meeting | AD6: 09/15/2026 | AE6: No | AF6: No | AG6: 1 | AH6: B ($500K-$1M) | AI6: Very High | AJ6: 9 | AK6: Steady annual renewal. Very loyal. | AL6: Lisa
A7: F-006 | B7: Naomi Ashford | C7: Ashford Philanthropic Group | D7: Foundation | E7: Stewardship | F7: Active | G7: nashford@ashfordphilanthropy.org | H7: (503) 555-7789 | I7: Pacific NW | J7: Major | K7: 04/22/2020 | L7: 60000 | M7: 80000 | N7: 100000 | O7: 110000 | P7: 78600 | Q7: =SUM(M7:P7) -> 368600 | R7: Yes | S7: 625000 | T7: FY2024 | U7: FY2028 | V7: 3 of 5 | W7: 125000 | X7: Ashford DAF - BNY Mellon | Y7: Rural Program Expansion | Z7: Maria Lopez | AA7: 03/15/2026 | AB7: Email | AC7: Send Q1 impact report | AD7: 04/10/2026 | AE7: No | AF7: Yes | AG7: 2 | AH7: B ($500K-$1M) | AI7: High | AJ7: 7 | AK7: Earmarked for rural expansion. Very engaged with program outcomes. | AL7: Rafaela
A8: F-007 | B8: Priya Ramanathan | C8: Ramanathan & Associates | D8: Corporate | E8: Stewardship | F8: Active | G8: priya@ramanathan-assoc.com | H8: (617) 555-4102 | I8: Northeast | J8: Mid-Level | K8: 08/15/2022 | L8: 25000 | M8: 25000 | N8: 35000 | O8: 50000 | P8: 53200 | Q8: =SUM(M8:P8) -> 163200 | R8: No | X8: Direct | Y8: STEM Education | Z8: James Wright | AA8: 02/03/2026 | AB8: Email | AC8: Thank you + impact report | AD8: 04/15/2026 | AE8: No | AF8: No | AG8: 1 | AH8: C ($100K-$500K) | AI8: High | AJ8: 8 | AK8: Referred by Margaret Chen. Increased from $50K to $75K this year. | AL8: Jack
A9: F-008 | B9: Michael & Patricia Novak | C9: Novak Family Foundation | D9: Foundation | E9: Stewardship | F9: Active | G9: mnovak@novakfamilyfdn.org | H9: (847) 555-4412 | I9: Midwest | J9: Mid-Level | K9: 02/20/2021 | L9: 40000 | M9: 50000 | N9: 65000 | O9: 75000 | P9: 68400 | Q9: =SUM(M9:P9) -> 258400 | R9: No | X9: Novak Family DAF - Community Foundation | Y9: Pell-Eligible Student Scholarships | Z9: Sarah Mitchell | AA9: 03/18/2026 | AB9: Phone call | AC9: Prepare renewal proposal | AD9: 05/01/2026 | AE9: No | AF9: No | AG9: 1 | AH9: B ($500K-$1M) | AI9: High | AJ9: 7 | AK9: Focus on Pell-eligible students in Midwest. Opportunity for programmatic partnership. | AL9: Lisa
A10: F-009 | B10: Sandra Okonkwo | C10: Okonkwo Ventures | D10: Corporate | E10: Cultivation | F10: Prospect | G10: sokonkwo@okonkwoventures.com | H10: (404) 555-1357 | I10: Southeast | J10: Mid-Level | K10: 02/14/2026 | L10: 50000 | M10: 0 | N10: 0 | O10: 0 | P10: 41900 | Q10: =SUM(M10:P10) -> 41900 | R10: No | X10: Direct | Y10: Scholarship Program | Z10: Maria Lopez | AA10: 02/14/2026 | AB10: Event follow-up | AC10: Schedule discovery meeting | AD10: 04/20/2026 | AE10: No | AF10: No | AG10: 1 | AH10: C ($100K-$500K) | AI10: Medium | AJ10: 6 | AK10: Event follow-up conversion. Shares interest in scholarship program with Gutierrez-Santos. | AL10: Lisa
A11: F-010 | B11: Thomas Fitzgerald | C11: Fitzgerald & Moore LLP | D11: Corporate | E11: Stewardship | F11: Active | G11: tfitzgerald@fitzmoore.com | H11: (202) 555-9088 | I11: Mid-Atlantic | J11: Mid-Level | K11: 05/10/2020 | L11: 15000 | M11: 15000 | N11: 20000 | O11: 25000 | P11: 17500 | Q11: =SUM(M11:P11) -> 77500 | R11: No | X11: Direct | Y11: Unrestricted + Pro Bono Legal | Z11: James Wright | AA11: 03/01/2026 | AB11: In-person meeting | AC11: Discuss pro bono capacity for next FY | AD11: 04/30/2026 | AE11: No | AF11: No | AG11: 2 | AH11: C ($100K-$500K) | AI11: High | AJ11: 7 | AK11: Also provides pro bono legal support. Referred Robert Blackwell III. | AL11: Lisa
A12: F-011 | B12: William R. Thornton | C12: Thornton Capital Partners | D12: Corporate | E12: Qualification | F12: Prospect | G12: wthornton@thorntoncap.com | H12: (646) 555-5521 | I12: Northeast | J12: Mid-Level | K12: 10/05/2025 | L12: 60000 | M12: 0 | N12: 0 | O12: 60000 | P12: 38100 | Q12: =SUM(M12:P12) -> 98100 | R12: No | X12: Direct | Y12: Unrestricted | Z12: James Wright | AA12: 03/10/2026 | AB12: In-person meeting | AC12: Send introductory materials | AD12: 04/15/2026 | AE12: No | AF12: No | AG12: 2 | AH12: A ($1M+) | AI12: Medium | AJ12: 9 | AK12: Strong board prospect. Requested meeting with ED. Deepening engagement since fall reception. | AL12: Lisa
A13: F-012 | B13: Evelyn Tran | C13: Tran Holdings LLC | D13: Corporate | E13: Cultivation | F13: Prospect | G13: evelyn.tran@tranholdings.com | H13: (408) 555-2106 | I13: West Coast | J13: Entry | K13: 12/01/2025 | L13: 35000 | M13: 0 | N13: 0 | O13: 35000 | P13: 23000 | Q13: =SUM(M13:P13) -> 58000 | R13: No | X13: Direct | Y13: Alumni Scholarship | Z13: Sarah Mitchell | AA13: 03/22/2026 | AB13: Email | AC13: Follow up on named scholarship fund interest | AD13: 04/30/2026 | AE13: No | AF13: No | AG13: 1 | AH13: A ($1M+) | AI13: Low | AJ13: 7 | AK13: Alumni, Class of 2005. Company just completed Series C. Interested in named scholarship fund. | AL13: Lisa
A14: F-013 | B14: Hiroshi Tanaka | C14: Tanaka Biotech Inc. | D14: Corporate | E14: Identification | F14: Prospect | G14: htanaka@tanakabiotech.com | H14: (858) 555-3891 | I14: West Coast | J14: None | M14: 0 | N14: 0 | O14: 0 | P14: 0 | Q14: =SUM(M14:P14) -> 0 | R14: No | Y14: STEM Education | Z14: Maria Lopez | AA14: 01/10/2026 | AB14: Research | AC14: Request intro through Margaret Chen | AD14: 04/15/2026 | AE14: No | AF14: No | AG14: 0 | AH14: A ($1M+) | AI14: Low | AJ14: 7 | AK14: UC San Diego connection. Biotech IPO 2024. Interested in STEM education per public statements. | AL14: Lisa
A15: F-014 | B15: Denise & Marcus Hargrove | C15: Hargrove Family Fund | D15: Individual/Family | E15: Identification | F15: Prospect | G15: dhargrove@hargrovefund.org | H15: (404) 555-8822 | I15: Southeast | J15: None | M15: 0 | N15: 0 | O15: 0 | P15: 0 | Q15: =SUM(M15:P15) -> 0 | R15: No | Z15: James Wright | AA15: 12/15/2025 | AB15: Research | AC15: Research capacity and interests | AD15: 05/01/2026 | AE15: No | AF15: No | AG15: 0 | AH15: B ($500K-$1M) | AI15: Low | AJ15: 7 | AK15: Atlanta-based philanthropy family. Focus on education equity. Identified via peer screening. | AL15: Jack
A16: F-015 | B16: Victoria Langston-Reed | C16: Reed Foundation | D16: Foundation | E16: Solicitation | F16: Prospect | G16: vlreed@reedfoundation.org | H16: (617) 555-6100 | I16: Northeast | J16: None | M16: 0 | N16: 0 | O16: 0 | P16: 0 | Q16: =SUM(M16:P16) -> 0 | R16: No | Y16: Scholarship / General | Z16: Sarah Mitchell | AA16: 03/28/2026 | AB16: Proposal submitted | AC16: Await foundation board decision | AD16: 06/01/2026 | AE16: No | AF16: No | AG16: 1 | AH16: A ($1M+) | AI16: Medium | AJ16: 6 | AK16: $200K proposal submitted for scholarship endowment. Foundation board meets quarterly. | AL16: Lisa
A17: F-016 | B17: Gregory & Susan Patel | C17: Patel Family Trust | D17: Individual/Family | E17: Re-engagement | F17: Lapsed | G17: gpatel@patelfamilytrust.org | H17: (312) 555-2200 | I17: Midwest | J17: Mid-Level | K17: 06/01/2018 | L17: 25000 | M17: 50000 | N17: 40000 | O17: 0 | P17: 0 | Q17: =SUM(M17:P17) -> 90000 | R17: No | X17: Patel Family DAF - Schwab | Y17: Unrestricted | Z17: James Wright | AA17: 11/20/2025 | AB17: Phone call (voicemail) | AC17: Send personalized re-engagement letter | AD17: 04/10/2026 | AE17: No | AF17: Yes (Former) | AG17: 0 | AH17: B ($500K-$1M) | AI17: Medium | AJ17: 8 | AK17: Last gift FY2024. Missed FY2025 renewal. Was on advisory council. Personal outreach needed. | AL17: Rafaela
A18: F-017 | B18: Diana Kowalski | C18: Kowalski Media Group | D18: Corporate | E18: Re-engagement | F18: Lapsed | G18: dkowalski@kowalskimedia.com | H18: (646) 555-4477 | I18: Northeast | J18: Entry | K18: 09/15/2020 | L18: 10000 | M18: 15000 | N18: 10000 | O18: 0 | P18: 0 | Q18: =SUM(M18:P18) -> 25000 | R18: No | X18: Direct | Y18: Unrestricted | Z18: Maria Lopez | AA18: 10/01/2025 | AB18: Email (no response) | AC18: Try phone outreach | AD18: 04/15/2026 | AE18: No | AF18: No | AG18: 0 | AH18: C ($100K-$500K) | AI18: Low | AJ18: 4 | AK18: Last gift FY2024. No response to renewal emails. Try phone. | AL18: Jack
A19: F-018 | B19: Lawrence Bennett | C19: Bennett Capital LLC | D19: Corporate | E19: Closed - Declined | F19: Inactive | G19: lbennett@bennettcap.com | H19: (415) 555-9900 | I19: West Coast | J19: None | M19: 0 | N19: 0 | O19: 0 | P19: 0 | Q19: =SUM(M19:P19) -> 0 | R19: No | Z19: Sarah Mitchell | AA19: 09/15/2025 | AB19: Phone call | AC19: Monitor; revisit in 18 months | AD19: 03/15/2027 | AE19: No | AF19: No | AG19: 1 | AH19: A ($1M+) | AI19: Very Low | AJ19: 7 | AK19: Declined after solicitation meeting. Cited other philanthropic priorities. Polite; door not closed. | AL19: Rafaela
A20: F-019 | B20: Catherine & James Moreau | C20: Moreau Foundation | D20: Foundation | E20: Stewardship | F20: Active | G20: cmoreau@moreaufoundation.org | H20: (504) 555-3321 | I20: Southeast | J20: Major | K20: 01/10/2019 | L20: 80000 | M20: 100000 | N20: 120000 | O20: 140000 | P20: 116500 | Q20: =SUM(M20:P20) -> 476500 | R20: Yes | S20: 800000 | T20: FY2024 | U20: FY2028 | V20: 3 of 5 | W20: 160000 | X20: Moreau Foundation DAF - Fidelity | Y20: First-Generation Student Support | Z20: Sarah Mitchell | AA20: 03/20/2026 | AB20: Phone call | AC20: Prepare cultivation strategy | AD20: 05/10/2026 | AE20: No | AF20: No | AG20: 2 | AH20: B ($500K-$1M) | AI20: Very High | AJ20: 9 | AK20: New Orleans-based. Deep interest in first-gen students. Annual site visits. | AL20: Jack
A21: F-020 | B21: Richard Cheng | C21: Cheng Dynamics | D21: Corporate | E21: Stewardship | F21: Active | G21: rcheng@chengdynamics.com | H21: (650) 555-8812 | I21: West Coast | J21: Mid-Level | K21: 03/01/2022 | L21: 30000 | M21: 30000 | N21: 45000 | O21: 55000 | P21: 49600 | Q21: =SUM(M21:P21) -> 179600 | R21: No | X21: Direct | Y21: STEM Education | Z21: Maria Lopez | AA21: 02/20/2026 | AB21: Email | AC21: Draft stewardship plan | AD21: 04/20/2026 | AE21: No | AF21: No | AG21: 2 | AH21: C ($100K-$500K) | AI21: High | AJ21: 5 | AK21: Growing engagement. Employee matching program potential. | AL21: Rafaela
A22: F-021 | B22: Amara Osei-Mensah | C22: Osei-Mensah Family Trust | D22: Individual/Family | E22: Stewardship | F22: Active | G22: aosei@oseimensah.org | H22: (770) 555-6644 | I22: Southeast | J22: Mid-Level | K22: 06/15/2021 | L22: 25000 | M22: 35000 | N22: 40000 | O22: 50000 | P22: 53200 | Q22: =SUM(M22:P22) -> 178200 | R22: No | X22: Osei-Mensah DAF - Vanguard | Y22: Scholarship Program | Z22: James Wright | AA22: 01/30/2026 | AB22: In-person meeting | AC22: Propose multi-year pledge | AD22: 04/25/2026 | AE22: No | AF22: No | AG22: 1 | AH22: B ($500K-$1M) | AI22: High | AJ22: 9 | AK22: Atlanta-based. Increasing annually. Ready for major gift conversation. | AL22: Jack
A23: F-022 | B23: Patricia & Leonard Dubois | C23: Dubois Charitable Fund | D23: Individual/Family | E23: Solicitation | F23: Active | G23: pdubois@duboisfund.org | H23: (617) 555-1198 | I23: Northeast | J23: Major | K23: 09/01/2017 | L23: 75000 | M23: 100000 | N23: 100000 | O23: 100000 | P23: 69800 | Q23: =SUM(M23:P23) -> 369800 | R23: Yes | S23: 500000 | T23: FY2023 | U23: FY2027 | V23: 4 of 5 | W23: 100000 | X23: Dubois DAF - BNY Mellon | Y23: Unrestricted | Z23: Sarah Mitchell | AA23: 12/15/2025 | AB23: Holiday card + call | AC23: Final pledge year discussion; renewal strategy | AD23: 06/01/2026 | AE23: Yes | AF23: No | AG23: 2 | AH23: A ($1M+) | AI23: Very High | AJ23: 10 | AK23: Board member. Entering final pledge year. Need to discuss renewal or increase. | AL23: Lisa
A24: F-023 | B24: Kenji & Yuki Watanabe | C24: Watanabe Group | D24: Corporate | E24: Cultivation | F24: Active | G24: kwatanabe@watanabegroup.co | H24: (206) 555-4455 | I24: Pacific NW | J24: Mid-Level | K24: 11/15/2024 | L24: 40000 | M24: 0 | N24: 0 | O24: 40000 | P24: 36900 | Q24: =SUM(M24:P24) -> 76900 | R24: No | X24: Direct | Y24: Rural Program | Z24: Maria Lopez | AA24: 03/01/2026 | AB24: In-person meeting | AC24: Tour rural program sites | AD24: 05/15/2026 | AE24: No | AF24: No | AG24: 1 | AH24: C ($100K-$500K) | AI24: Medium | AJ24: 6 | AK24: Seattle-based. Second gift indicates deepening. Schedule site visit. | AL24: Lisa
A25: F-024 | B25: Helen Markovich | C25: Markovich Partners LLC | D25: Corporate | E25: Stewardship | F25: Active | G25: hmarkovich@markovichpartners.com | H25: (312) 555-7733 | I25: Midwest | J25: Mid-Level | K25: 04/20/2020 | L25: 20000 | M25: 25000 | N25: 30000 | O25: 35000 | P25: 36900 | Q25: =SUM(M25:P25) -> 126900 | R25: No | X25: Direct | Y25: Unrestricted | Z25: James Wright | AA25: 02/10/2026 | AB25: Email | AC25: Send FY2026 impact summary | AD25: 04/15/2026 | AE25: No | AF25: Yes | AG25: 2 | AH25: C ($100K-$500K) | AI25: High | AJ25: 7 | AK25: Advisory council member. Consistent growth. Midwest business network connections. | AL25: Lisa
A26: F-025 | B26: Raj & Sunita Kapoor | C26: Kapoor Family Foundation | D26: Foundation | E26: Solicitation | F26: Active | G26: rkapoor@kapoorfamilyfdn.org | H26: (713) 555-9922 | I26: Southwest | J26: Major | K26: 02/28/2020 | L26: 50000 | M26: 75000 | N26: 90000 | O26: 100000 | P26: 84300 | Q26: =SUM(M26:P26) -> 349300 | R26: Yes | S26: 600000 | T26: FY2025 | U26: FY2029 | V26: 2 of 5 | W26: 120000 | X26: Kapoor Family DAF - Goldman Sachs | Y26: STEM Education Pipeline | Z26: Maria Lopez | AA26: 03/10/2026 | AB26: Phone call | AC26: Initial outreach call | AD26: 04/10/2026 | AE26: No | AF26: No | AG26: 2 | AH26: A ($1M+) | AI26: High | AJ26: 8 | AK26: Houston-based. Strong alignment with STEM pipeline. Want to see expansion to Texas. | AL26: Lisa
A27: F-026 | B27: Franklin & Anne Beaumont | C27: Beaumont Group | D27: Individual/Family | E27: Solicitation | F27: Prospect | G27: fbeaumont@beaumontgroup.com | H27: (214) 555-2288 | I27: Southwest | J27: Mid-Level | K27: 07/01/2021 | L27: 20000 | M27: 25000 | N27: 30000 | O27: 40000 | P27: 38400 | Q27: =SUM(M27:P27) -> 133400 | R27: No | X27: Direct | Y27: General Scholarship | Z27: Sarah Mitchell | AA27: 01/15/2026 | AB27: Holiday card + call | AC27: Annual renewal ask | AD27: 09/01/2026 | AE27: No | AF27: No | AG27: 1 | AH27: C ($100K-$500K) | AI27: High | AJ27: 7 | AK27: Dallas-based. Reliable renewals. Potential for multi-year commitment. | AL27: Jack
A28: F-027 | B28: Nadia El-Amin | C28: El-Amin Consulting Group | D28: Corporate | E28: Stewardship | F28: Active | G28: nelamin@elamingroup.com | H28: (202) 555-6655 | I28: Mid-Atlantic | J28: Entry | K28: 10/01/2023 | L28: 10000 | M28: 0 | N28: 0 | O28: 10000 | P28: 12300 | Q28: =SUM(M28:P28) -> 22300 | R28: No | X28: Direct | Y28: Unrestricted | Z28: James Wright | AA28: 03/15/2026 | AB28: Email | AC28: Cultivation lunch | AD28: 05/01/2026 | AE28: No | AF28: No | AG28: 1 | AH28: C ($100K-$500K) | AI28: Medium | AJ28: 7 | AK28: DC-based consultant. Growing engagement. Connected to policy networks. | AL28: Lisa
A29: F-028 | B29: George & Linda Stratton | C29: Stratton Industries | D29: Corporate | E29: Qualification | F29: Prospect | G29: gstratton@strattonindustries.com | H29: (704) 555-1122 | I29: Southeast | J29: None | M29: 0 | N29: 0 | O29: 0 | P29: 0 | Q29: =SUM(M29:P29) -> 0 | R29: No | Y29: Unrestricted | Z29: James Wright | AA29: 02/01/2026 | AB29: Research | AC29: Request meeting through Thornton connection | AD29: 04/20/2026 | AE29: No | AF29: No | AG29: 0 | AH29: A ($1M+) | AI29: Low | AJ29: 7 | AK29: Charlotte manufacturing. Peer connection through William Thornton. Philanthropic history in education. | AL29: Lisa
A30: F-029 | B30: Isabelle Fontaine | C30: Fontaine Arts & Education Trust | D30: Foundation | E30: Cultivation | F30: Prospect | G30: ifontaine@fontainetrust.org | H30: (415) 555-5567 | I30: West Coast | J30: None | M30: 0 | N30: 0 | O30: 0 | P30: 0 | Q30: =SUM(M30:P30) -> 0 | R30: No | Y30: Arts + STEM Integration | Z30: Sarah Mitchell | AA30: 03/25/2026 | AB30: In-person meeting | AC30: Submit LOI for arts-STEM integration grant | AD30: 05/01/2026 | AE30: No | AF30: No | AG30: 1 | AH30: B ($500K-$1M) | AI30: Medium | AJ30: 5 | AK30: SF-based trust focused on arts and education. Met at conference. Very aligned with new arts-STEM program. | AL30: Lisa
A31: F-030 | B31: Marcus & Tanya Robinson | C31: Robinson Legacy Fund | D31: Individual/Family | E31: Identification | F31: Prospect | G31: mrobinson@robinsonlegacy.org | H31: (404) 555-8890 | I31: Southeast | J31: None | M31: 0 | N31: 0 | O31: 0 | P31: 0 | Q31: =SUM(M31:P31) -> 0 | R31: No | Z31: Maria Lopez | AA31: 01/20/2026 | AB31: Research | AC31: Add to annual gala invite list | AD31: 04/15/2026 | AE31: No | AF31: No | AG31: 0 | AH31: B ($500K-$1M) | AI31: Low | AJ31: 6 | AK31: Atlanta philanthropists. Education equity focus. Identified through Hargrove network. | AL31: Jack
A32: F-031 | B32: Dr. Angela Vasquez-Torres | C32: Vasquez-Torres Medical Foundation | D32: Foundation | E32: Solicitation | F32: Prospect | G32: avasquez@vtmedfoundation.org | H32: (305) 555-7712 | I32: Southeast | J32: None | M32: 0 | N32: 0 | O32: 0 | P32: 0 | Q32: =SUM(M32:P32) -> 0 | R32: No | Y32: Health Sciences Scholarship | Z32: James Wright | AA32: 03/30/2026 | AB32: Proposal submitted | AC32: Follow up after board review | AD32: 06/15/2026 | AE32: No | AF32: No | AG32: 1 | AH32: B ($500K-$1M) | AI32: Medium | AJ32: 5 | AK32: $150K proposal for health sciences scholarships. Miami-based. Board meets in June. | AL32: Rafaela
A33: F-032 | B33: Arthur & Elaine Worthington | C33: Worthington Trust | D33: Individual/Family | E33: Qualification | F33: Prospect | G33: aworthington@worthingtontrust.com | H33: (860) 555-3344 | I33: Northeast | J33: None | M33: 0 | N33: 0 | O33: 0 | P33: 0 | Q33: =SUM(M33:P33) -> 0 | R33: No | Y33: Endowment | Z33: Sarah Mitchell | AA33: 02/10/2026 | AB33: Phone call | AC33: Schedule campus visit | AD33: 04/25/2026 | AE33: No | AF33: No | AG33: 0 | AH33: A ($1M+) | AI33: Low | AJ33: 5 | AK33: Connecticut old money. Endowment-focused giving. Warm intro from Dubois. | AL33: Lisa
A34: F-033 | B34: Carmen Delgado-Ruiz | C34: Delgado Enterprises | D34: Corporate | E34: Qualification | F34: Prospect | G34: cdelgado@delgadoenterprises.com | H34: (210) 555-4411 | I34: Southwest | J34: Entry | K34: 12/15/2025 | L34: 15000 | M34: 0 | N34: 0 | O34: 0 | P34: 10000 | Q34: =SUM(M34:P34) -> 10000 | R34: No | X34: Direct | Y34: STEM Education | Z34: Maria Lopez | AA34: 12/15/2025 | AB34: Event follow-up | AC34: Schedule coffee meeting | AD34: 04/15/2026 | AE34: No | AF34: No | AG34: 1 | AH34: C ($100K-$500K) | AI34: Medium | AJ34: 4 | AK34: San Antonio-based. Initial gift at holiday event. Tech company founder. STEM aligned. | AL34: Rafaela
A35: F-034 | B35: Howard & Jean Prescott | C35: Prescott Foundation | D35: Foundation | E35: Re-engagement | F35: Lapsed | G35: hprescott@prescottfdn.org | H35: (203) 555-6677 | I35: Northeast | J35: Major | K35: 03/01/2016 | L35: 100000 | M35: 120000 | N35: 100000 | O35: 50000 | P35: 0 | Q35: =SUM(M35:P35) -> 270000 | R35: No | X35: Prescott DAF - Northern Trust | Y35: Unrestricted | Z35: Sarah Mitchell | AA35: 11/01/2025 | AB35: Phone call | AC35: ED personal outreach call | AD35: 04/10/2026 | AE35: No | AF35: Yes (Former) | AG35: 0 | AH35: A ($1M+) | AI35: Medium | AJ35: 8 | AK35: Declined from $120K to $50K in FY2025, then lapsed. Former advisory council. Personal call from ED needed. | AL35: Lisa
A36: F-035 | B36: Tomoko Nakamura | C36: Nakamura Design Studio | D36: Corporate | E36: Re-engagement | F36: Lapsed | G36: tnakamura@nakamuradesign.com | H36: (503) 555-2233 | I36: Pacific NW | J36: Entry | K36: 08/01/2022 | L36: 10000 | M36: 10000 | N36: 15000 | O36: 10000 | P36: 0 | Q36: =SUM(M36:P36) -> 35000 | R36: No | X36: Direct | Y36: Unrestricted | Z36: Maria Lopez | AA36: 09/15/2025 | AB36: Email (no response) | AC36: Send personalized project update | AD36: 04/15/2026 | AE36: No | AF36: No | AG36: 0 | AH36: C ($100K-$500K) | AI36: Low | AJ36: 5 | AK36: Portland designer. Gave 3 years. No response to renewal. Try project-specific appeal. | AL36: Rafaela
A37: F-036 | B37: Robert & Christine Andersen | C37: Andersen Family Fund | D37: Individual/Family | E37: Re-engagement | F37: Lapsed | G37: randersen@andersenfund.org | H37: (952) 555-8811 | I37: Midwest | J37: Mid-Level | K37: 05/15/2019 | L37: 30000 | M37: 40000 | N37: 50000 | O37: 0 | P37: 0 | Q37: =SUM(M37:P37) -> 90000 | R37: No | X37: Andersen DAF - Schwab | Y37: Pell-Eligible Scholarships | Z37: James Wright | AA37: 10/20/2025 | AB37: Phone call (voicemail) | AC37: Handwritten note from scholarship recipient | AD37: 04/20/2026 | AE37: No | AF37: No | AG37: 0 | AH37: B ($500K-$1M) | AI37: Medium | AJ37: 7 | AK37: Minneapolis family. Cared about Pell students. Missed FY2025. Try scholarship recipient story. | AL37: Lisa
A38: F-037 | B38: Martin & Louise Kessler | C38: Kessler Group | D38: Corporate | E38: Closed - Declined | F38: Inactive | G38: mkessler@kesslergroup.com | H38: (212) 555-0099 | I38: Northeast | J38: None | M38: 0 | N38: 0 | O38: 0 | P38: 0 | Q38: =SUM(M38:P38) -> 0 | R38: No | Z38: James Wright | AA38: 06/01/2025 | AB38: In-person meeting | AC38: Revisit in 2027 | AD38: 01/15/2027 | AE38: No | AF38: No | AG38: 0 | AH38: A ($1M+) | AI38: Very Low | AJ38: 7 | AK38: Declined. Company restructuring. Said to revisit in 2 years. | AL38: Jack
A39: F-038 | B39: Diane Zhao | C39: Zhao Capital Management | D39: Corporate | E39: Closed - Declined | F39: Inactive | G39: dzhao@zhaocapital.com | H39: (646) 555-3388 | I39: Northeast | J39: None | M39: 0 | N39: 0 | O39: 0 | P39: 0 | Q39: =SUM(M39:P39) -> 0 | R39: No | Z39: Sarah Mitchell | AA39: 08/15/2025 | AB39: Email | AC39: Initial outreach call | AD39: 08/15/2026 | AE39: No | AF39: No | AG39: 1 | AH39: B ($500K-$1M) | AI39: Very Low | AJ39: 3 | AK39: Politely declined. Prefers arts funding. Keep on radar for arts-STEM if program launches. | AL39: Lisa
A40: F-039 | B40: Jonathan & Claire Harrington | C40: Harrington Charitable Trust | D40: Individual/Family | E40: Stewardship | F40: Active | G40: jharrington@harringtontrust.org | H40: (617) 555-8834 | I40: Northeast | J40: Major | K40: 05/20/2018 | L40: 60000 | M40: 80000 | N40: 90000 | O40: 100000 | P40: 88900 | Q40: =SUM(M40:P40) -> 358900 | R40: Yes | S40: 550000 | T40: FY2025 | U40: FY2029 | V40: 2 of 5 | W40: 110000 | X40: Harrington DAF - Fidelity | Y40: First-Generation Students | Z40: Sarah Mitchell | AA40: 03/01/2026 | AB40: In-person meeting | AC40: Annual pledge check-in | AD40: 05/20/2026 | AE40: No | AF40: Yes | AG40: 3 | AH40: A ($1M+) | AI40: High | AJ40: 8 | AK40: Boston-based. Advisory council. Strong advocates. Host annual donor dinner. | AL40: Jack
A41: F-040 | B41: Lena Volkov | C41: Volkov Tech Foundation | D41: Foundation | E41: Stewardship | F41: Active | G41: lvolkov@volkovtech.org | H41: (408) 555-1199 | I41: West Coast | J41: Mid-Level | K41: 01/15/2023 | L41: 25000 | M41: 0 | N41: 0 | O41: 25000 | P41: 32400 | Q41: =SUM(M41:P41) -> 57400 | R41: No | X41: Direct | Y41: STEM Education | Z41: Maria Lopez | AA41: 02/15/2026 | AB41: Email | AC41: Review giving history | AD41: 04/20/2026 | AE41: No | AF41: No | AG41: 1 | AH41: C ($100K-$500K) | AI41: High | AJ41: 7 | AK41: Silicon Valley tech exec. Doubling down on STEM. Potential for corporate partnership. | AL41: Rafaela
A42: F-041 | B42: Oscar & Valentina Cruz | C42: Cruz Community Fund | D42: Individual/Family | E42: Stewardship | F42: Active | G42: ocruz@cruzfund.org | H42: (213) 555-7766 | I42: West Coast | J42: Mid-Level | K42: 08/01/2020 | L42: 20000 | M42: 25000 | N42: 30000 | O42: 35000 | P42: 35000 | Q42: =SUM(M42:P42) -> 125000 | R42: No | X42: Cruz DAF - Schwab | Y42: Rural Program | Z42: Maria Lopez | AA42: 01/20/2026 | AB42: Phone call | AC42: Invite to rural site visit | AD42: 05/15/2026 | AE42: No | AF42: No | AG42: 2 | AH42: C ($100K-$500K) | AI42: High | AJ42: 8 | AK42: LA-based. Consistent growth. Passionate about rural access. | AL42: Rafaela
A43: F-042 | B43: Sebastian Reeves | C43: Reeves Holdings International | D43: Corporate | E43: Cultivation | F43: Active | G43: sreeves@reevesholdings.com | H43: (305) 555-4488 | I43: Southeast | J43: Mid-Level | K43: 09/01/2024 | L43: 30000 | M43: 0 | N43: 0 | O43: 0 | P43: 24100 | Q43: =SUM(M43:P43) -> 24100 | R43: No | X43: Direct | Y43: Northeast Programs | Z43: James Wright | AA43: 03/05/2026 | AB43: In-person meeting | AC43: Discuss multi-year partnership | AD43: 05/01/2026 | AE43: No | AF43: No | AG43: 1 | AH43: B ($500K-$1M) | AI43: Medium | AJ43: 5 | AK43: Miami-based. International holdings. Second gift expected Q2. | AL43: Jack
A44: F-043 | B44: Miriam Goldstein-Levy | C44: Goldstein-Levy Philanthropic Fund | D44: Individual/Family | E44: Stewardship | F44: Active | G44: mgoldstein@glfund.org | H44: (212) 555-5544 | I44: Northeast | J44: Major | K44: 11/15/2017 | L44: 75000 | M44: 90000 | N44: 100000 | O44: 110000 | P44: 79600 | Q44: =SUM(M44:P44) -> 379600 | R44: Yes | S44: 600000 | T44: FY2024 | U44: FY2028 | V44: 3 of 5 | W44: 120000 | X44: Goldstein-Levy DAF - Goldman Sachs | Y44: Scholarship Endowment | Z44: Sarah Mitchell | AA44: 03/18/2026 | AB44: Phone call | AC44: Draft stewardship plan | AD44: 04/30/2026 | AE44: No | AF44: No | AG44: 2 | AH44: A ($1M+) | AI44: Very High | AJ44: 10 | AK44: NYC philanthropist. Interested in naming a scholarship endowment. High-touch stewardship needed. | AL44: Jack
A45: F-044 | B45: Derek & Monique Baptiste | C45: Baptiste Family Foundation | D45: Foundation | E45: Stewardship | F45: Active | G45: dbaptiste@baptistefdn.org | H45: (786) 555-3300 | I45: Southeast | J45: Mid-Level | K45: 03/15/2022 | L45: 20000 | M45: 20000 | N45: 30000 | O45: 35000 | P45: 37600 | Q45: =SUM(M45:P45) -> 122600 | R45: No | X45: Direct | Y45: Pell-Eligible Students | Z45: Maria Lopez | AA45: 02/28/2026 | AB45: Email | AC45: Connect with Novak re: Pell focus | AD45: 04/15/2026 | AE45: No | AF45: No | AG45: 1 | AH45: C ($100K-$500K) | AI45: High | AJ45: 6 | AK45: Miami. Haitian-American family. Strong Pell focus. Could partner with Novak Foundation. | AL45: Rafaela
A46: F-045 | B46: Elizabeth Hawthorne | C46: Hawthorne Media Corp | D46: Corporate | E46: Solicitation | F46: Prospect | G46: ehawthorne@hawthornecorp.com | H46: (310) 555-2277 | I46: West Coast | J46: Entry | K46: 06/01/2024 | L46: 15000 | M46: 0 | N46: 0 | O46: 0 | P46: 9500 | Q46: =SUM(M46:P46) -> 9500 | R46: No | X46: Direct | Y46: Unrestricted | Z46: Sarah Mitchell | AA46: 12/01/2025 | AB46: Event follow-up | AC46: Invite to Q2 donor event | AD46: 05/01/2026 | AE46: No | AF46: No | AG46: 1 | AH46: B ($500K-$1M) | AI46: Low | AJ46: 7 | AK46: Media exec. Initial gift at gala. High capacity but early stage. | AL46: Rafaela
A47: F-046 | B47: Andrew & Susan Pemberton | C47: Pemberton Investments | D47: Corporate | E47: Identification | F47: Prospect | G47: apemberton@pembertoninvest.com | H47: (704) 555-9977 | I47: Southeast | J47: None | M47: 0 | N47: 0 | O47: 0 | P47: 0 | Q47: =SUM(M47:P47) -> 0 | R47: No | Z47: James Wright | AA47: 02/20/2026 | AB47: Research | AC47: Cold outreach via annual appeal | AD47: 05/01/2026 | AE47: No | AF47: No | AG47: 0 | AH47: A ($1M+) | AI47: Very Low | AJ47: 7 | AK47: Charlotte PE firm. Education giving in other contexts. Peer-screened. | AL47: Jack
A48: F-047 | B48: Maya Singh-Patel | C48: Singh-Patel Ventures | D48: Corporate | E48: Qualification | F48: Prospect | G48: msingh@singhpatelvc.com | H48: (415) 555-6688 | I48: West Coast | J48: Entry | K48: 01/30/2026 | L48: 10000 | M48: 0 | N48: 0 | O48: 0 | P48: 8300 | Q48: =SUM(M48:P48) -> 8300 | R48: No | X48: Direct | Y48: STEM Education | Z48: Maria Lopez | AA48: 01/30/2026 | AB48: Event follow-up | AC48: Coffee meeting to learn interests | AD48: 04/20/2026 | AE48: No | AF48: No | AG48: 1 | AH48: C ($100K-$500K) | AI48: Medium | AJ48: 7 | AK48: SF VC partner. Initial gift at winter event. STEM aligned. Early cultivation. | AL48: Rafaela
A49: F-048 | B49: Raymond & Barbara O'Sullivan | C49: O'Sullivan Family Foundation | D49: Foundation | E49: Solicitation | F49: Prospect | G49: rosullivan@osullivanfdn.org | H49: (312) 555-5500 | I49: Midwest | J49: None | M49: 0 | N49: 0 | O49: 0 | P49: 0 | Q49: =SUM(M49:P49) -> 0 | R49: No | Y49: General Scholarship | Z49: Sarah Mitchell | AA49: 03/28/2026 | AB49: Proposal submitted | AC49: Await response; follow up June | AD49: 06/10/2026 | AE49: No | AF49: No | AG49: 1 | AH49: A ($1M+) | AI49: Medium | AJ49: 7 | AK49: $250K proposal for general scholarship fund. Chicago foundation. Board meets quarterly in June. | AL49: Lisa
A50: F-049 | B50: Ingrid Johansson-Berg | C50: Nordic Education Initiative | D50: Foundation | E50: Qualification | F50: Prospect | G50: ijohansson@nordicedu.org | H50: (612) 555-7700 | I50: Midwest | J50: None | M50: 0 | N50: 0 | O50: 0 | P50: 0 | Q50: =SUM(M50:P50) -> 0 | R50: No | Y50: International Student Support | Z50: James Wright | AA50: 03/15/2026 | AB50: Phone call | AC50: Schedule campus tour for board | AD50: 05/01/2026 | AE50: No | AF50: No | AG50: 0 | AH50: B ($500K-$1M) | AI50: Medium | AJ50: 7 | AK50: Minneapolis-based Nordic foundation. Focus on international education exchange. New prospect. | AL50: Lisa
A51: F-050 | B51: Terrence & Alma Washington-Greene | C51: Washington-Greene Family Trust | D51: Individual/Family | E51: Cultivation | F51: Prospect | G51: twashington@wgfamilytrust.org | H51: (202) 555-1144 | I51: Mid-Atlantic | J51: Entry | K51: 11/01/2025 | L51: 20000 | M51: 0 | N51: 0 | O51: 0 | P51: 13600 | Q51: =SUM(M51:P51) -> 13600 | R51: No | X51: Direct | Y51: Education Equity | Z51: James Wright | AA51: 11/15/2025 | AB51: Event follow-up | AC51: Invite to DC donor circle | AD51: 04/15/2026 | AE51: No | AF51: No | AG51: 1 | AH51: A ($1M+) | AI51: Low | AJ51: 7 | AK51: DC-based. Initial gift at fall event. Known philanthropists in education equity. | AL51: Jack
A52: F-051 | B52: Steven & Marie Lindqvist | C52: Lindqvist Group | D52: Corporate | E52: Re-engagement | F52: Lapsed | G52: slindqvist@lindqvistgroup.com | H52: (206) 555-8800 | I52: Pacific NW | J52: Mid-Level | K52: 02/01/2019 | L52: 25000 | M52: 35000 | N52: 40000 | O52: 25000 | P52: 0 | Q52: =SUM(M52:P52) -> 100000 | R52: No | X52: Direct | Y52: Unrestricted | Z52: Maria Lopez | AA52: 10/15/2025 | AB52: Phone call | AC52: Personal note from ED with program update | AD52: 04/20/2026 | AE52: No | AF52: No | AG52: 0 | AH52: B ($500K-$1M) | AI52: Medium | AJ52: 5 | AK52: Seattle. Declined from $40K to $25K then lapsed. May be tied to company financials. | AL52: Lisa
A53: F-052 | B53: Claudia Ferreira-Santos | C53: Ferreira-Santos Associates | D53: Corporate | E53: Re-engagement | F53: Lapsed | G53: cferreira@fsassociates.com | H53: (617) 555-9933 | I53: Northeast | J53: Entry | K53: 07/01/2021 | L53: 10000 | M53: 10000 | N53: 15000 | O53: 0 | P53: 0 | Q53: =SUM(M53:P53) -> 25000 | R53: No | X53: Direct | Y53: STEM Education | Z53: James Wright | AA53: 09/01/2025 | AB53: Email (no response) | AC53: Try LinkedIn outreach | AD53: 04/15/2026 | AE53: No | AF53: No | AG53: 0 | AH53: C ($100K-$500K) | AI53: Low | AJ53: 3 | AK53: Boston consulting firm. 3-year donor. No response to emails. Try alternative channels. | AL53: Jack
A54: F-053 | B54: Philip & Janet Rothschild-Murray | C54: Rothschild-Murray Trust | D54: Individual/Family | E54: Closed - Declined | F54: Inactive | G54: prothschild@rmtrust.org | H54: (860) 555-2211 | I54: Northeast | J54: None | M54: 0 | N54: 0 | O54: 0 | P54: 0 | Q54: =SUM(M54:P54) -> 0 | R54: No | Z54: Sarah Mitchell | AA54: 07/01/2025 | AB54: Phone call | AC54: Follow up on event attendance | AD54: 01/15/2027 | AE54: No | AF54: No | AG54: 0 | AH54: A ($1M+) | AI54: Very Low | AJ54: 7 | AK54: Connecticut. Declined due to existing education commitments. Revisit via Worthington intro. | AL54: Jack
A55: F-054 | B55: Grace Okafor-Williams | C55: Okafor-Williams Group | D55: Corporate | E55: Closed - Declined | F55: Inactive | G55: gokafor@owgroup.com | H55: (404) 555-1177 | I55: Southeast | J55: None | M55: 0 | N55: 0 | O55: 0 | P55: 0 | Q55: =SUM(M55:P55) -> 0 | R55: No | Z55: Maria Lopez | AA55: 05/15/2025 | AB55: In-person meeting | AC55: Revisit if arts-STEM program launches | AD55: 09/01/2026 | AE55: No | AF55: No | AG55: 1 | AH55: B ($500K-$1M) | AI55: Very Low | AJ55: 5 | AK55: Atlanta. Prefers arts-focused philanthropy. Could revisit if arts-STEM integration launches. | AL55: Lisa
A56: F-055 | B56: Dr. Samuel Adeyemi | C56: Adeyemi Health Sciences Trust | D56: Foundation | E56: Identification | F56: Prospect | G56: sadeyemi@adeyemitrust.org | H56: (713) 555-0011 | I56: Southwest | J56: None | M56: 0 | N56: 0 | O56: 0 | P56: 0 | Q56: =SUM(M56:P56) -> 0 | R56: No | Y56: Health Sciences | Z56: Maria Lopez | AA56: 03/01/2026 | AB56: Research | AC56: Request intro through Vasquez-Torres | AD56: 04/30/2026 | AE56: No | AF56: No | AG56: 0 | AH56: B ($500K-$1M) | AI56: Low | AJ56: 5 | AK56: Houston physician-philanthropist. Health education focus. Connected to Vasquez-Torres network. | AL56: Rafaela
A57: F-056 | B57: Jessica & Ryan Calloway | C57: Calloway Ventures | D57: Corporate | E57: Identification | F57: Prospect | G57: jcalloway@callowayvc.com | H57: (512) 555-2299 | I57: Southwest | J57: None | M57: 0 | N57: 0 | O57: 0 | P57: 0 | Q57: =SUM(M57:P57) -> 0 | R57: No | Z57: James Wright | AA57: 02/15/2026 | AB57: Research | AC57: Add to Austin donor event invite | AD57: 05/01/2026 | AE57: No | AF57: No | AG57: 0 | AH57: A ($1M+) | AI57: Very Low | AJ57: 5 | AK57: Austin VC firm. IPO exit 2025. No philanthropic history identified yet. Peer-screened. | AL57: Lisa
A58: F-057 | B58: Nadine Brosseau | C58: Brosseau Family Fund | D58: Individual/Family | E58: Qualification | F58: Prospect | G58: nbrosseau@brosseaufund.org | H58: (504) 555-6633 | I58: Southeast | J58: None | M58: 0 | N58: 0 | O58: 0 | P58: 0 | Q58: =SUM(M58:P58) -> 0 | R58: No | Y58: Education Equity | Z58: Sarah Mitchell | AA58: 03/10/2026 | AB58: Phone call | AC58: Schedule intro lunch | AD58: 04/20/2026 | AE58: No | AF58: No | AG58: 0 | AH58: B ($500K-$1M) | AI58: Medium | AJ58: 7 | AK58: New Orleans family wealth. Education equity interest. Warm lead from Moreau. | AL58: Jack
A59: F-058 | B59: Timothy & Andrea Park-Saunders | C59: Park-Saunders Foundation | D59: Foundation | E59: Cultivation | F59: Prospect | G59: tpark@parksaundersfdn.org | H59: (206) 555-8877 | I59: Pacific NW | J59: Entry | K59: 02/01/2026 | L59: 10000 | M59: 0 | N59: 0 | O59: 0 | P59: 6000 | Q59: =SUM(M59:P59) -> 6000 | R59: No | X59: Direct | Y59: Rural Program | Z59: Maria Lopez | AA59: 02/01/2026 | AB59: Event follow-up | AC59: Thank you call + site visit invite | AD59: 04/15/2026 | AE59: No | AF59: No | AG59: 1 | AH59: B ($500K-$1M) | AI59: Medium | AJ59: 5 | AK59: Seattle foundation. Initial gift at winter gala. Rural education aligned. | AL59: Rafaela
A60: F-059 | B60: Cynthia Abrams-Klein | C60: Abrams-Klein Charitable Trust | D60: Individual/Family | E60: Solicitation | F60: Prospect | G60: cabrams@akcharitable.org | H60: (212) 555-4400 | I60: Northeast | J60: None | M60: 0 | N60: 0 | O60: 0 | P60: 0 | Q60: =SUM(M60:P60) -> 0 | R60: No | Y60: Scholarship Endowment | Z60: Sarah Mitchell | AA60: 03/25/2026 | AB60: Proposal submitted | AC60: Follow up post-review in May | AD60: 05/15/2026 | AE60: No | AF60: No | AG60: 2 | AH60: A ($1M+) | AI60: High | AJ60: 7 | AK60: $300K endowment proposal. NYC philanthropist. Multiple cultivation meetings completed. Strong alignment. | AL60: Jack
A61: F-060 | B61: Marcus Jennings | C61: Jennings Capital Group | D61: Corporate | E61: Identification | F61: Prospect | G61: mjennings@jenningscapital.com | H61: (704) 555-3355 | I61: Southeast | J61: None | M61: 0 | N61: 0 | O61: 0 | P61: 0 | Q61: =SUM(M61:P61) -> 0 | R61: No | Z61: James Wright | AA61: 01/15/2026 | AB61: Research | AC61: Peer screening complete; request intro via Stratton | AD61: 04/30/2026 | AE61: No | AF61: No | AG61: 0 | AH61: A ($1M+) | AI61: Low | AJ61: 6 | AK61: Charlotte finance. Peer-screened. Education history on other boards. Stratton connection. | AL61: Lisa
A62: F-061 | B62: Dr. Wei & Jennifer Liu-Chang | C62: Liu-Chang Education Foundation | D62: Foundation | E62: Cultivation | F62: Prospect | G62: wliu@liuchangfdn.org | H62: (650) 555-1177 | I62: West Coast | J62: Entry | K62: 11/15/2025 | L62: 25000 | M62: 0 | N62: 0 | O62: 0 | P62: 15700 | Q62: =SUM(M62:P62) -> 15700 | R62: No | X62: Direct | Y62: STEM Education | Z62: Maria Lopez | AA62: 01/15/2026 | AB62: In-person meeting | AC62: Submit LOI for STEM grant | AD62: 04/15/2026 | AE62: No | AF62: No | AG62: 1 | AH62: A ($1M+) | AI62: Medium | AJ62: 7 | AK62: Palo Alto. Tech fortune. $25K initial gift. Foundation has $50M+ in assets. High potential. | AL62: Rafaela
A63: F-062 | B63: Natasha Orlova-Petrov | C63: Orlova-Petrov Arts & Sciences Fund | D63: Foundation | E63: Qualification | F63: Prospect | G63: norlova@opfund.org | H63: (312) 555-6622 | I63: Midwest | J63: None | M63: 0 | N63: 0 | O63: 0 | P63: 0 | Q63: =SUM(M63:P63) -> 0 | R63: No | Y63: Arts-STEM Integration | Z63: James Wright | AA63: 02/28/2026 | AB63: Phone call | AC63: Explore arts-STEM alignment | AD63: 04/25/2026 | AE63: No | AF63: No | AG63: 0 | AH63: B ($500K-$1M) | AI63: Medium | AJ63: 7 | AK63: Chicago. Arts + sciences intersection. Could be perfect fit if arts-STEM program launches. | AL63: Jack
A64: F-063 | B64: Brandon & Tiffany Maxwell | C64: Maxwell Legacy Foundation | D64: Foundation | E64: Cultivation | F64: Prospect | G64: bmaxwell@maxwelllegacy.org | H64: (404) 555-9944 | I64: Southeast | J64: Entry | K64: 12/01/2025 | L64: 20000 | M64: 0 | N64: 0 | O64: 0 | P64: 13800 | Q64: =SUM(M64:P64) -> 13800 | R64: No | X64: Direct | Y64: First-Generation Students | Z64: Maria Lopez | AA64: 12/15/2025 | AB64: Event follow-up | AC64: Campus visit + scholar meeting | AD64: 05/01/2026 | AE64: No | AF64: No | AG64: 1 | AH64: B ($500K-$1M) | AI64: Medium | AJ64: 7 | AK64: Atlanta. Both first-gen college. Deep personal connection to mission. $20K initial gift promising. | AL64: Lisa
A65: F-064 | B65: Eleanor Whitmore-Davis | C65: Whitmore-Davis Trust | D65: Individual/Family | E65: Solicitation | F65: Prospect | G65: ewhitmore@wdtrust.org | H65: (860) 555-7788 | I65: Northeast | J65: None | M65: 0 | N65: 0 | O65: 0 | P65: 0 | Q65: =SUM(M65:P65) -> 0 | R65: No | Y65: Unrestricted Endowment | Z65: Sarah Mitchell | AA65: 03/20/2026 | AB65: Proposal submitted | AC65: Board review in June | AD65: 06/15/2026 | AE65: No | AF65: No | AG65: 2 | AH65: A ($1M+) | AI65: Medium | AJ65: 6 | AK65: $500K unrestricted endowment proposal. Connecticut. Worthington referral. Long cultivation cycle. | AL65: Jack
A66: F-065 | B66: Roberto & Ana Castillo-Vega | C66: Castillo-Vega Enterprises | D66: Corporate | E66: Identification | F66: Prospect | G66: rcastillo@cventerprises.com | H66: (210) 555-5588 | I66: Southwest | J66: None | M66: 0 | N66: 0 | O66: 0 | P66: 0 | Q66: =SUM(M66:P66) -> 0 | R66: No | Z66: Maria Lopez | AA66: 02/01/2026 | AB66: Research | AC66: Review giving history | AD66: 05/15/2026 | AE66: No | AF66: No | AG66: 0 | AH66: C ($100K-$500K) | AI66: Low | AJ66: 5 | AK66: San Antonio manufacturing. Hispanic business leader. Education philanthropy unknown. Cold prospect. | AL66: Lisa
A67: F-066 | B67: Dr. Priscilla Oduya | C67: Oduya Global Education Fund | D67: Foundation | E67: Identification | F67: Prospect | G67: poduya@oduyafund.org | H67: (202) 555-3366 | I67: Mid-Atlantic | J67: None | M67: 0 | N67: 0 | O67: 0 | P67: 0 | Q67: =SUM(M67:P67) -> 0 | R67: No | Y67: International Student Scholarships | Z67: James Wright | AA67: 03/15/2026 | AB67: Phone call | AC67: Explore international scholarship alignment | AD67: 04/30/2026 | AE67: No | AF67: No | AG67: 0 | AH67: B ($500K-$1M) | AI67: Medium | AJ67: 6 | AK67: DC-based global education fund. Focus on African diaspora students. New contact via conference. | AL67: Jack
A68: F-067 | B68: Alan & Deborah Sinclair | C68: Sinclair Timber Company | D68: Corporate | E68: Cultivation | F68: Prospect | G68: asinclair@sinclairtimber.com | H68: (503) 555-1155 | I68: Pacific NW | J68: Entry | K68: 01/15/2026 | L68: 15000 | M68: 0 | N68: 0 | O68: 0 | P68: 11800 | Q68: =SUM(M68:P68) -> 11800 | R68: No | X68: Direct | Y68: Rural Program | Z68: Maria Lopez | AA68: 01/20/2026 | AB68: Phone call | AC68: Site visit to rural program in Oregon | AD68: 05/01/2026 | AE68: No | AF68: No | AG68: 1 | AH68: C ($100K-$500K) | AI68: Medium | AJ68: 7 | AK68: Portland timber company. Rural communities connection. $15K at winter event. Very aligned with rural program. | AL68: Lisa
A69: F-068 | B69: Vanessa & Michael Torres-Rubin | C69: Torres-Rubin Family Fund | D69: Individual/Family | E69: Identification | F69: Prospect | G69: vtorres@trfamilyfund.org | H69: (305) 555-8844 | I69: Southeast | J69: None | M69: 0 | N69: 0 | O69: 0 | P69: 0 | Q69: =SUM(M69:P69) -> 0 | R69: No | Z69: James Wright | AA69: 03/01/2026 | AB69: Research | AC69: Annual appeal mailing + gala invite | AD69: 05/01/2026 | AE69: No | AF69: No | AG69: 0 | AH69: C ($100K-$500K) | AI69: Low | AJ69: 6 | AK69: Miami family fund. Identified through Baptiste network. Education giving elsewhere. | AL69: Jack
A70: F-069 | B70: Christine Yamamoto | C70: Yamamoto Tech Ventures | D70: Corporate | E70: Qualification | F70: Prospect | G70: cyamamoto@yamatech.com | H70: (408) 555-3377 | I70: West Coast | J70: Entry | K70: 02/15/2026 | L70: 10000 | M70: 0 | N70: 0 | O70: 0 | P70: 8300 | Q70: =SUM(M70:P70) -> 8300 | R70: No | X70: Direct | Y70: STEM Education | Z70: Maria Lopez | AA70: 02/20/2026 | AB70: Email | AC70: Share STEM program outcomes deck | AD70: 04/15/2026 | AE70: No | AF70: No | AG70: 1 | AH70: C ($100K-$500K) | AI70: Medium | AJ70: 5 | AK70: San Jose. Tech exec. Initial gift online. Follow up with personal outreach. | AL70: Rafaela
A71: F-070 | B71: Edward & Margaret Blackstone | C71: Blackstone Heritage Foundation | D71: Foundation | E71: Solicitation | F71: Prospect | G71: eblackstone@blackstonehf.org | H71: (617) 555-4422 | I71: Northeast | J71: None | M71: 0 | N71: 0 | O71: 0 | P71: 0 | Q71: =SUM(M71:P71) -> 0 | R71: No | Y71: General Scholarship | Z71: Sarah Mitchell | AA71: 03/30/2026 | AB71: Proposal submitted | AC71: Await foundation decision in July | AD71: 07/01/2026 | AE71: No | AF71: No | AG71: 1 | AH71: A ($1M+) | AI71: Medium | AJ71: 9 | AK71: $400K scholarship proposal. Boston heritage foundation. Slow-moving board. Dubois provided introduction. | AL71: Lisa
A72: F-071 | B72: Patricia Nguyen-Thompson | C72: Nguyen-Thompson Associates | D72: Corporate | E72: Qualification | F72: Prospect | G72: pnguyen@ntassociates.com | H72: (714) 555-9900 | I72: West Coast | J72: None | M72: 0 | N72: 0 | O72: 0 | P72: 0 | Q72: =SUM(M72:P72) -> 0 | R72: No | Y72: STEM Education | Z72: Maria Lopez | AA72: 03/20/2026 | AB72: Phone call | AC72: Intro meeting scheduled | AD72: 04/22/2026 | AE72: No | AF72: No | AG72: 0 | AH72: C ($100K-$500K) | AI72: Medium | AJ72: 4 | AK72: Orange County consulting. Anh Nguyen (scholarship alum) works there. Organic connection. | AL72: Lisa
A73: F-072 | B73: Dmitri & Svetlana Ivanov | C73: Ivanov Family Trust | D73: Individual/Family | E73: Identification | F73: Prospect | G73: divanov@ivanovtrust.com | H73: (646) 555-7711 | I73: Northeast | J73: None | M73: 0 | N73: 0 | O73: 0 | P73: 0 | Q73: =SUM(M73:P73) -> 0 | R73: No | Z73: James Wright | AA73: 02/10/2026 | AB73: Research | AC73: Cold outreach via annual appeal | AD73: 05/01/2026 | AE73: No | AF73: No | AG73: 0 | AH73: A ($1M+) | AI73: Very Low | AJ73: 4 | AK73: NYC finance family. Wealth screening flagged. No known education philanthropy. Very early stage. | AL73: Jack
A74: F-073 | B74: Monique St. Claire | C74: St. Claire Education Partners | D74: Corporate | E74: Cultivation | F74: Prospect | G74: mstclaire@stclaireedu.com | H74: (504) 555-2244 | I74: Southeast | J74: Entry | K74: 01/30/2026 | L74: 10000 | M74: 0 | N74: 0 | O74: 0 | P74: 8000 | Q74: =SUM(M74:P74) -> 8000 | R74: No | X74: Direct | Y74: Education Equity | Z74: Maria Lopez | AA74: 02/05/2026 | AB74: Event follow-up | AC74: Coffee meeting in New Orleans | AD74: 04/15/2026 | AE74: No | AF74: No | AG74: 1 | AH74: C ($100K-$500K) | AI74: Medium | AJ74: 4 | AK74: NOLA education consulting firm. $10K at winter event. Mission-aligned business. | AL74: Jack
A75: F-074 | B75: Daniel & Rebecca Hoffman | C75: Hoffman Associates | D75: Corporate | E75: Stewardship | F75: Active | G75: dhoffman@hoffmanassoc.com | H75: (312) 555-0044 | I75: Midwest | J75: Entry | K75: 09/01/2023 | L75: 10000 | M75: 0 | N75: 0 | O75: 10000 | P75: 9500 | Q75: =SUM(M75:P75) -> 19500 | R75: No | X75: Direct | Y75: Unrestricted | Z75: James Wright | AA75: 12/01/2025 | AB75: Holiday card + call | AC75: Upgrade ask at spring event | AD75: 05/15/2026 | AE75: No | AF75: No | AG75: 1 | AH75: C ($100K-$500K) | AI75: Medium | AJ75: 5 | AK75: Chicago consulting. Year 3. Slow but steady growth. | AL75: Lisa
A76: F-075 | B76: Lucia Mendoza-Garcia | C76: Mendoza-Garcia Foundation | D76: Foundation | E76: Stewardship | F76: Active | G76: lmendoza@mgfoundation.org | H76: (213) 555-8833 | I76: West Coast | J76: Mid-Level | K76: 04/01/2021 | L76: 20000 | M76: 25000 | N76: 30000 | O76: 35000 | P76: 40500 | Q76: =SUM(M76:P76) -> 130500 | R76: No | X76: Mendoza-Garcia DAF - Schwab | Y76: First-Generation Students | Z76: Maria Lopez | AA76: 03/10/2026 | AB76: Phone call | AC76: Propose multi-year commitment | AD76: 05/01/2026 | AE76: No | AF76: No | AG76: 2 | AH76: C ($100K-$500K) | AI76: High | AJ76: 6 | AK76: LA-based. First-gen focus. Consistent growth. Ready for multi-year conversation. | AL76: Rafaela
A77: F-076 | B77: Warren & Doris Carmichael | C77: Carmichael Trust | D77: Individual/Family | E77: Re-engagement | F77: Lapsed | G77: wcarmichael@carmichaeltrust.org | H77: (847) 555-6699 | I77: Midwest | J77: Mid-Level | K77: 01/15/2018 | L77: 30000 | M77: 35000 | N77: 40000 | O77: 20000 | P77: 0 | Q77: =SUM(M77:P77) -> 95000 | R77: No | X77: Carmichael DAF - Vanguard | Y77: Unrestricted | Z77: Sarah Mitchell | AA77: 11/01/2025 | AB77: Phone call | AC77: Prepare cultivation strategy | AD77: 04/15/2026 | AE77: No | AF77: Yes (Former) | AG77: 0 | AH77: B ($500K-$1M) | AI77: Medium | AJ77: 7 | AK77: Evanston IL. Declined sharply then lapsed. Former advisory council. Health issues may be factor; handle sensitively. | AL77: Lisa
A78: F-077 | B78: Jacqueline DuPont-Williams | C78: DuPont-Williams Group | D78: Corporate | E78: Re-engagement | F78: Lapsed | G78: jdupont@dpwgroup.com | H78: (202) 555-7744 | I78: Mid-Atlantic | J78: Entry | K78: 06/01/2022 | L78: 10000 | M78: 10000 | N78: 15000 | O78: 0 | P78: 0 | Q78: =SUM(M78:P78) -> 25000 | R78: No | X78: Direct | Y78: Unrestricted | Z78: James Wright | AA78: 10/01/2025 | AB78: Email (no response) | AC78: LinkedIn message + personal note | AD78: 04/20/2026 | AE78: No | AF78: No | AG78: 0 | AH78: C ($100K-$500K) | AI78: Low | AJ78: 4 | AK78: DC consulting. 3-year donor. Company may have downsized. Try personal channel. | AL78: Jack
A79: F-078 | B79: Gordon & Lillian Ashworth | C79: Ashworth Family Trust | D79: Individual/Family | E79: Closed - Declined | F79: Inactive | G79: gashworth@ashworthtrust.org | H79: (203) 555-0022 | I79: Northeast | J79: None | M79: 0 | N79: 0 | O79: 0 | P79: 0 | Q79: =SUM(M79:P79) -> 0 | R79: No | Z79: Sarah Mitchell | AA79: 04/01/2025 | AB79: Phone call | AC79: Long-term monitor; possible estate gift prospect | AD79: 01/01/2027 | AE79: No | AF79: No | AG79: 0 | AH79: A ($1M+) | AI79: Very Low | AJ79: 4 | AK79: Greenwich CT. Declined politely. Mentioned us in estate planning conversations per advisor. Very long-term. | AL79: Jack
A80: F-079 | B80: Reginald Barnes | C80: Barnes Logistics Corp | D80: Corporate | E80: Closed - Declined | F80: Inactive | G80: rbarnes@barneslogistics.com | H80: (773) 555-5566 | I80: Midwest | J80: None | M80: 0 | N80: 0 | O80: 0 | P80: 0 | Q80: =SUM(M80:P80) -> 0 | R80: No | Z80: James Wright | AA80: 07/15/2025 | AB80: Email | AC80: Annual newsletter only | AD80: 07/15/2026 | AE80: No | AF80: No | AG80: 0 | AH80: C ($100K-$500K) | AI80: Very Low | AJ80: 2 | AK80: Chicago logistics. Declined. Budget constraints. Keep on newsletter. | AL80: Jack
A81: F-080 | B81: Katherine & Paul Remington-Hall | C81: Remington-Hall Charitable Fund | D81: Individual/Family | E81: Closed - Declined | F81: Inactive | G81: kremington@rhfund.org | H81: (860) 555-1188 | I81: Northeast | J81: None | M81: 0 | N81: 0 | O81: 0 | P81: 0 | Q81: =SUM(M81:P81) -> 0 | R81: No | Z81: Sarah Mitchell | AA81: 05/01/2025 | AB81: In-person meeting | AC81: Revisit when arts-STEM launches | AD81: 09/01/2026 | AE81: No | AF81: No | AG81: 1 | AH81: A ($1M+) | AI81: Very Low | AJ81: 5 | AK81: Connecticut. Arts-focused. Declined because no arts component. Could revisit with arts-STEM program. | AL81: Jack

Sheet Pipeline Summary
A1: Funder Pipeline Summary
A3: By Status | B3: Count | C3: Total Lifetime Giving
A4: Active | B4: =COUNTIF('Funder Database April'!F:F,"Active") -> 28 | C4: =SUMIF('Funder Database April'!F:F,"Active",'Funder Database April'!Q:Q) -> 8060000
A5: Prospect | B5: =COUNTIF('Funder Database April'!F:F,"Prospect") -> 35 | C5: =SUMIF('Funder Database April'!F:F,"Prospect",'Funder Database April'!Q:Q) -> 325000
A6: Lapsed | B6: =COUNTIF('Funder Database April'!F:F,"Lapsed") -> 9 | C6: =SUMIF('Funder Database April'!F:F,"Lapsed",'Funder Database April'!Q:Q) -> 755000
A7: Inactive | B7: =COUNTIF('Funder Database April'!F:F,"Inactive") -> 8 | C7: =SUMIF('Funder Database April'!F:F,"Inactive",'Funder Database April'!Q:Q) -> 0
A8: Total | B8: =SUM(B4:B7) -> 80 | C8: =SUM(C4:C7) -> 9140000
A10: By Stage | B10: Count
A11: Identification | B11: =COUNTIF('Funder Database April'!E:E,"Identification") -> 10
A12: Qualification | B12: =COUNTIF('Funder Database April'!E:E,"Qualification") -> 8
A13: Cultivation | B13: =COUNTIF('Funder Database April'!E:E,"Cultivation") -> 15
A14: Solicitation | B14: =COUNTIF('Funder Database April'!E:E,"Solicitation") -> 6
A15: Stewardship | B15: =COUNTIF('Funder Database April'!E:E,"Stewardship") -> 24
A16: Re-engagement | B16: =COUNTIF('Funder Database April'!E:E,"Re-engagement") -> 9
A17: Closed - Declined | B17: =COUNTIF('Funder Database April'!E:E,"Closed - Declined") -> 8
A19: FY2026 YTD Giving | B19: =SUM('Funder Database April'!P:P) -> 2925000
